<Ship version="1" liftedOff="0" touchingGround="0"><DisconnectedParts><DisconnectedPart><Parts><Part partType="detacher-2" id="146595" x="4.750000" y="2.500000" angle="0.000000" angleV="0.000000" editorAngle="0" activated="0" exploded="0" flippedX="0" flippedY="0"/><Part partType="lander-1" id="146596" x="4.250000" y="2.250000" angle="0.000000" angleV="0.000000" editorAngle="0" activated="0" exploded="0" flippedX="0" flippedY="0" lower="0" raise="0" length="2.260000" legAngle="-628316.312500"/></Parts><Connections><Connection parentAttachPoint="1" childAttachPoint="2" parentPart="146595" childPart="146596"/></Connections></DisconnectedPart><DisconnectedPart><Parts><Part partType="detacher-2" id="152097" x="5.250000" y="4.500000" angle="0.000000" angleV="0.000000" editorAngle="0" activated="0" exploded="0" flippedX="0" flippedY="0"/><Part partType="lander-1" id="152098" x="5.750000" y="4.250000" angle="0.000000" angleV="0.000000" editorAngle="0" activated="0" exploded="0" flippedX="0" flippedY="0" lower="0" raise="0" length="2.260000" legAngle="628316.312500"/></Parts><Connections><Connection parentAttachPoint="2" childAttachPoint="1" parentPart="152097" childPart="152098"/></Connections></DisconnectedPart><DisconnectedPart><Parts><Part partType="detacher-1" id="152915" x="28.000000" y="-27.750000" angle="0.000000" angleV="0.000000" editorAngle="0" activated="0" exploded="0" flippedX="0" flippedY="0"/><Part partType="fueltank-2" id="152916" x="28.000000" y="-29.000000" angle="4.712389" angleV="0.000000" editorAngle="3"><Tank fuel="3000.000000"/></Part><Part partType="fueltank-3" id="152861" x="27.000000" y="-32.000000" angle="0.000000" angleV="0.000000" editorAngle="0"><Tank fuel="6000.000000"/></Part><Part partType="fueltank-3" id="152929" x="27.000000" y="-40.000000" angle="0.000000" angleV="0.000000" editorAngle="0"><Tank fuel="6000.000000"/></Part><Part partType="engine-3" id="152930" x="27.000000" y="-42.000000" angle="0.000000" angleV="0.000000" editorAngle="0" activated="0" exploded="0" flippedX="0" flippedY="0"><Engine fuel="0.000000"/></Part><Part partType="detacher-1" id="152925" x="27.000000" y="-44.250000" angle="0.000000" angleV="0.000000" editorAngle="0" activated="0" exploded="0" flippedX="0" flippedY="0"/><Part partType="engine-4" id="152926" x="27.000000" y="-51.000000" angle="0.000000" angleV="0.000000" editorAngle="0" activated="0" exploded="0" flippedX="0" flippedY="0"><Engine fuel="9000.000000"/></Part><Part partType="engine-4" id="152927" x="27.000000" y="-51.000000" angle="0.000000" angleV="0.000000" editorAngle="0" activated="0" exploded="0" flippedX="0" flippedY="0"><Engine fuel="9000.000000"/></Part><Part partType="nosecone-1" id="152920" x="25.500000" y="-56.500000" angle="1.570796" angleV="0.000000" editorAngle="1" activated="0" exploded="0" flippedX="0" flippedY="0"/><Part partType="fueltank-3" id="152906" x="29.000000" y="-32.000000" angle="0.000000" angleV="0.000000" editorAngle="0"><Tank fuel="6000.000000"/></Part><Part partType="fueltank-3" id="152932" x="29.000000" y="-40.000000" angle="0.000000" angleV="0.000000" editorAngle="0"><Tank fuel="6000.000000"/></Part><Part partType="engine-3" id="152933" x="29.000000" y="-42.000000" angle="0.000000" angleV="0.000000" editorAngle="0" activated="0" exploded="0" flippedX="0" flippedY="0"><Engine fuel="0.000000"/></Part><Part partType="detacher-1" id="152922" x="29.000000" y="-44.250000" angle="0.000000" angleV="0.000000" editorAngle="0" activated="0" exploded="0" flippedX="0" flippedY="0"/><Part partType="engine-4" id="152923" x="29.000000" y="-51.000000" angle="0.000000" angleV="0.000000" editorAngle="0" activated="0" exploded="0" flippedX="0" flippedY="0"><Engine fuel="9000.000000"/></Part><Part partType="engine-4" id="152924" x="29.000000" y="-51.000000" angle="0.000000" angleV="0.000000" editorAngle="0" activated="0" exploded="0" flippedX="0" flippedY="0"><Engine fuel="9000.000000"/></Part><Part partType="nosecone-1" id="152918" x="30.500000" y="-56.500000" angle="4.712389" angleV="0.000000" editorAngle="3" activated="0" exploded="0" flippedX="0" flippedY="0"/></Parts><Connections><Connection parentAttachPoint="2" childAttachPoint="3" parentPart="152915" childPart="152916"/><Connection parentAttachPoint="3" childAttachPoint="1" parentPart="152916" childPart="152861"/><Connection parentAttachPoint="2" childAttachPoint="1" parentPart="152861" childPart="152929"/><Connection parentAttachPoint="2" childAttachPoint="1" parentPart="152929" childPart="152930"/><Connection parentAttachPoint="2" childAttachPoint="1" parentPart="152930" childPart="152925"/><Connection parentAttachPoint="2" childAttachPoint="1" parentPart="152925" childPart="152926"/><Connection parentAttachPoint="2" childAttachPoint="2" parentPart="152926" childPart="152927"/><Connection parentAttachPoint="3" childAttachPoint="1" parentPart="152926" childPart="152920"/><Connection parentAttachPoint="3" childAttachPoint="1" parentPart="152916" childPart="152906"/><Connection parentAttachPoint="2" childAttachPoint="1" parentPart="152906" childPart="152932"/><Connection parentAttachPoint="2" childAttachPoint="1" parentPart="152932" childPart="152933"/><Connection parentAttachPoint="2" childAttachPoint="1" parentPart="152933" childPart="152922"/><Connection parentAttachPoint="2" childAttachPoint="1" parentPart="152922" childPart="152923"/><Connection parentAttachPoint="2" childAttachPoint="2" parentPart="152923" childPart="152924"/><Connection parentAttachPoint="4" childAttachPoint="1" parentPart="152923" childPart="152918"/></Connections></DisconnectedPart><DisconnectedPart><Parts><Part partType="fueltank-2" id="1146066" x="13.500000" y="32.500000" angle="0.000000" angleV="0.000000" editorAngle="0"><Tank fuel="3000.000000"/></Part><Part partType="engine-3" id="1146067" x="13.500000" y="28.500000" angle="0.000000" angleV="0.000000" editorAngle="0" activated="0" exploded="0" flippedX="0" flippedY="0"><Engine fuel="0.000000"/></Part><Part partType="nosecone-1" id="1146068" x="15.000000" y="33.500000" angle="4.712389" angleV="0.000000" editorAngle="3" activated="0" exploded="0" flippedX="0" flippedY="0"/><Part partType="nosecone-1" id="1146069" x="15.000000" y="31.500000" angle="4.712389" angleV="0.000000" editorAngle="3" activated="0" exploded="0" flippedX="0" flippedY="0"/></Parts><Connections><Connection parentAttachPoint="2" childAttachPoint="1" parentPart="1146066" childPart="1146067"/><Connection parentAttachPoint="4" childAttachPoint="1" parentPart="1146066" childPart="1146068"/><Connection parentAttachPoint="4" childAttachPoint="1" parentPart="1146066" childPart="1146069"/></Connections></DisconnectedPart></DisconnectedParts><Parts><Part partType="pod-1" id="1" x="0.000000" y="12.750000" angle="0.000000" angleV="0.000000" editorAngle="0"><Pod throttle="0.000000" name=""><Staging currentStage="0"><Step><Activate Id="1146035" moved="1"/><Activate Id="1146036" moved="1"/><Activate Id="1146037" moved="1"/><Activate Id="1146041" moved="1"/><Activate Id="1146042" moved="1"/><Activate Id="1146043" moved="1"/><Activate Id="1146047" moved="1"/><Activate Id="1146048" moved="1"/><Activate Id="1146049" moved="1"/><Activate Id="1146053" moved="1"/><Activate Id="1146054" moved="1"/><Activate Id="1146055" moved="1"/><Activate Id="1146021" moved="1"/><Activate Id="1146022" moved="1"/><Activate Id="1146023" moved="1"/><Activate Id="1146027" moved="1"/><Activate Id="1146028" moved="1"/><Activate Id="1146029" moved="1"/><Activate Id="1146014" moved="1"/><Activate Id="1146015" moved="1"/><Activate Id="1146016" moved="1"/><Activate Id="1145993" moved="1"/><Activate Id="1145997" moved="1"/><Activate Id="1145998" moved="1"/><Activate Id="1146033" moved="1"/><Activate Id="1146039" moved="1"/><Activate Id="1146045" moved="1"/><Activate Id="1146051" moved="1"/><Activate Id="1146019" moved="1"/><Activate Id="1146025" moved="1"/><Activate Id="1146010" moved="1"/><Activate Id="1146012" moved="1"/><Activate Id="1145991" moved="1"/></Step><Step><Activate Id="1146088" moved="0"/></Step><Step><Activate Id="146732" moved="1"/><Activate Id="143723" moved="1"/></Step></Staging></Pod></Part><Part partType="detacher-1" id="146732" x="0.000000" y="14.500000" angle="0.000000" angleV="0.000000" editorAngle="0" activated="0" exploded="0" flippedX="0" flippedY="0"/><Part partType="parachute-1" id="143723" x="0.000000" y="14.500000" angle="3.141593" angleV="0.000000" editorAngle="2" activated="0" exploded="0" flippedX="0" flippedY="0" chuteX="0.000000" chuteY="13.250000" chuteAngle="0.000000" chuteHeight="0.000000" inflation="0.100000" inflate="0" deployed="0" rope="0"/><Part partType="rcs-1" id="143728" x="-0.750000" y="13.750000" angle="0.000000" angleV="0.000000" editorAngle="0" activated="0" exploded="0" flippedX="1" flippedY="0"/><Part partType="rcs-1" id="143729" x="0.750000" y="13.750000" angle="0.000000" angleV="0.000000" editorAngle="0" activated="0" exploded="0" flippedX="0" flippedY="0"/><Part partType="rcs-1" id="143732" x="-1.250000" y="14.250000" angle="0.000000" angleV="0.000000" editorAngle="0" activated="0" exploded="0" flippedX="1" flippedY="0"/><Part partType="rcs-1" id="143731" x="1.250000" y="14.250000" angle="0.000000" angleV="0.000000" editorAngle="0" activated="0" exploded="0" flippedX="0" flippedY="0"/><Part partType="rcs-1" id="143733" x="-0.250000" y="13.750000" angle="0.000000" angleV="0.000000" editorAngle="0" activated="0" exploded="0" flippedX="1" flippedY="0"/><Part partType="rcs-1" id="143734" x="0.250000" y="13.750000" angle="0.000000" angleV="0.000000" editorAngle="0" activated="0" exploded="0" flippedX="0" flippedY="0"/><Part partType="nosecone-1" id="143738" x="-0.500000" y="15.500000" angle="0.000000" angleV="0.000000" editorAngle="0" activated="0" exploded="0" flippedX="0" flippedY="0"/><Part partType="nosecone-1" id="143739" x="0.500000" y="15.500000" angle="0.000000" angleV="0.000000" editorAngle="0" activated="0" exploded="0" flippedX="0" flippedY="0"/><Part partType="nosecone-1" id="143740" x="0.000000" y="15.500000" angle="0.000000" angleV="0.000000" editorAngle="0" activated="0" exploded="0" flippedX="0" flippedY="0"/><Part partType="nosecone-1" id="143741" x="-0.500000" y="15.500000" angle="0.000000" angleV="0.000000" editorAngle="0" activated="0" exploded="0" flippedX="0" flippedY="0"/><Part partType="nosecone-1" id="143742" x="0.500000" y="15.500000" angle="0.000000" angleV="0.000000" editorAngle="0" activated="0" exploded="0" flippedX="0" flippedY="0"/><Part partType="nosecone-1" id="143743" x="0.000000" y="15.500000" angle="0.000000" angleV="0.000000" editorAngle="0" activated="0" exploded="0" flippedX="0" flippedY="0"/><Part partType="nosecone-1" id="143744" x="-0.500000" y="15.500000" angle="0.000000" angleV="0.000000" editorAngle="0" activated="0" exploded="0" flippedX="0" flippedY="0"/><Part partType="nosecone-1" id="143745" x="0.500000" y="15.500000" angle="0.000000" angleV="0.000000" editorAngle="0" activated="0" exploded="0" flippedX="0" flippedY="0"/><Part partType="nosecone-1" id="143746" x="0.000000" y="15.500000" angle="0.000000" angleV="0.000000" editorAngle="0" activated="0" exploded="0" flippedX="0" flippedY="0"/><Part partType="nosecone-1" id="143747" x="0.500000" y="15.500000" angle="0.000000" angleV="0.000000" editorAngle="0" activated="0" exploded="0" flippedX="0" flippedY="0"/><Part partType="nosecone-1" id="143748" x="-0.500000" y="15.500000" angle="0.000000" angleV="0.000000" editorAngle="0" activated="0" exploded="0" flippedX="0" flippedY="0"/><Part partType="nosecone-1" id="143749" x="0.000000" y="15.500000" angle="0.000000" angleV="0.000000" editorAngle="0" activated="0" exploded="0" flippedX="0" flippedY="0"/><Part partType="nosecone-1" id="143783" x="0.000000" y="14.500000" angle="3.141593" angleV="0.000000" editorAngle="2" activated="0" exploded="0" flippedX="0" flippedY="0"/><Part partType="nosecone-1" id="143784" x="0.500000" y="15.500000" angle="0.000000" angleV="0.000000" editorAngle="0" activated="0" exploded="0" flippedX="0" flippedY="0"/><Part partType="nosecone-1" id="143785" x="-0.500000" y="15.500000" angle="0.000000" angleV="0.000000" editorAngle="0" activated="0" exploded="0" flippedX="0" flippedY="0"/><Part partType="nosecone-1" id="143786" x="0.000000" y="15.500000" angle="0.000000" angleV="0.000000" editorAngle="0" activated="0" exploded="0" flippedX="0" flippedY="0"/><Part partType="nosecone-1" id="143787" x="1.000000" y="14.500000" angle="4.712389" angleV="0.000000" editorAngle="3" activated="0" exploded="0" flippedX="0" flippedY="0"/><Part partType="nosecone-1" id="143788" x="1.000000" y="14.500000" angle="4.712389" angleV="0.000000" editorAngle="3" activated="0" exploded="0" flippedX="0" flippedY="0"/><Part partType="nosecone-1" id="143789" x="1.000000" y="14.500000" angle="4.712389" angleV="0.000000" editorAngle="3" activated="0" exploded="0" flippedX="0" flippedY="0"/><Part partType="nosecone-1" id="143790" x="-1.000000" y="14.500000" angle="1.570796" angleV="0.000000" editorAngle="1" activated="0" exploded="0" flippedX="0" flippedY="0"/><Part partType="nosecone-1" id="143791" x="-1.000000" y="14.500000" angle="1.570796" angleV="0.000000" editorAngle="1" activated="0" exploded="0" flippedX="0" flippedY="0"/><Part partType="nosecone-1" id="143792" x="-1.000000" y="14.500000" angle="1.570796" angleV="0.000000" editorAngle="1" activated="0" exploded="0" flippedX="0" flippedY="0"/><Part partType="nosecone-1" id="143793" x="0.000000" y="14.500000" angle="4.712389" angleV="0.000000" editorAngle="3" activated="0" exploded="0" flippedX="0" flippedY="0"/><Part partType="nosecone-1" id="143794" x="0.000000" y="14.500000" angle="4.712389" angleV="0.000000" editorAngle="3" activated="0" exploded="0" flippedX="0" flippedY="0"/><Part partType="nosecone-1" id="143795" x="0.000000" y="14.500000" angle="4.712389" angleV="0.000000" editorAngle="3" activated="0" exploded="0" flippedX="0" flippedY="0"/><Part partType="nosecone-1" id="143797" x="0.000000" y="14.500000" angle="1.570796" angleV="0.000000" editorAngle="1" activated="0" exploded="0" flippedX="0" flippedY="0"/><Part partType="nosecone-1" id="143796" x="0.000000" y="14.500000" angle="1.570796" angleV="0.000000" editorAngle="1" activated="0" exploded="0" flippedX="0" flippedY="0"/><Part partType="nosecone-1" id="143798" x="0.000000" y="14.500000" angle="1.570796" angleV="0.000000" editorAngle="1" activated="0" exploded="0" flippedX="0" flippedY="0"/><Part partType="nosecone-1" id="143799" x="-0.500000" y="15.500000" angle="0.000000" angleV="0.000000" editorAngle="0" activated="0" exploded="0" flippedX="0" flippedY="0"/><Part partType="nosecone-1" id="143801" x="0.500000" y="15.500000" angle="0.000000" angleV="0.000000" editorAngle="0" activated="0" exploded="0" flippedX="0" flippedY="0"/><Part partType="nosecone-1" id="143802" x="0.500000" y="15.500000" angle="0.000000" angleV="0.000000" editorAngle="0" activated="0" exploded="0" flippedX="0" flippedY="0"/><Part partType="nosecone-1" id="143803" x="-0.500000" y="15.500000" angle="0.000000" angleV="0.000000" editorAngle="0" activated="0" exploded="0" flippedX="0" flippedY="0"/><Part partType="nosecone-1" id="143804" x="0.000000" y="15.500000" angle="0.000000" angleV="0.000000" editorAngle="0" activated="0" exploded="0" flippedX="0" flippedY="0"/><Part partType="nosecone-1" id="143811" x="-0.500000" y="14.500000" angle="3.141593" angleV="0.000000" editorAngle="2" activated="0" exploded="0" flippedX="0" flippedY="0"/><Part partType="nosecone-1" id="143812" x="0.500000" y="14.500000" angle="3.141593" angleV="0.000000" editorAngle="2" activated="0" exploded="0" flippedX="0" flippedY="0"/><Part partType="nosecone-1" id="143813" x="-0.500000" y="14.500000" angle="3.141593" angleV="0.000000" editorAngle="2" activated="0" exploded="0" flippedX="0" flippedY="0"/><Part partType="nosecone-1" id="143814" x="0.500000" y="14.500000" angle="3.141593" angleV="0.000000" editorAngle="2" activated="0" exploded="0" flippedX="0" flippedY="0"/><Part partType="nosecone-1" id="143815" x="-0.500000" y="14.500000" angle="3.141593" angleV="0.000000" editorAngle="2" activated="0" exploded="0" flippedX="0" flippedY="0"/><Part partType="nosecone-1" id="143816" x="0.500000" y="14.500000" angle="3.141593" angleV="0.000000" editorAngle="2" activated="0" exploded="0" flippedX="0" flippedY="0"/><Part partType="nosecone-1" id="143824" x="-0.500000" y="14.500000" angle="0.000000" angleV="0.000000" editorAngle="0" activated="0" exploded="0" flippedX="0" flippedY="0"/><Part partType="nosecone-1" id="143818" x="-0.500000" y="13.500000" angle="3.141593" angleV="0.000000" editorAngle="2" activated="0" exploded="0" flippedX="0" flippedY="0"/><Part partType="nosecone-1" id="143819" x="0.500000" y="14.500000" angle="0.000000" angleV="0.000000" editorAngle="0" activated="0" exploded="0" flippedX="0" flippedY="0"/><Part partType="nosecone-1" id="143820" x="0.500000" y="13.500000" angle="3.141593" angleV="0.000000" editorAngle="2" activated="0" exploded="0" flippedX="0" flippedY="0"/><Part partType="nosecone-1" id="143821" x="0.000000" y="13.500000" angle="3.141593" angleV="0.000000" editorAngle="2" activated="0" exploded="0" flippedX="0" flippedY="0"/><Part partType="nosecone-1" id="143822" x="0.000000" y="13.500000" angle="3.141593" angleV="0.000000" editorAngle="2" activated="0" exploded="0" flippedX="0" flippedY="0"/><Part partType="nosecone-1" id="143823" x="0.000000" y="13.500000" angle="3.141593" angleV="0.000000" editorAngle="2" activated="0" exploded="0" flippedX="0" flippedY="0"/><Part partType="nosecone-1" id="143826" x="0.000000" y="14.500000" angle="0.000000" angleV="0.000000" editorAngle="0" activated="0" exploded="0" flippedX="0" flippedY="0"/><Part partType="nosecone-1" id="143828" x="0.000000" y="14.500000" angle="0.000000" angleV="0.000000" editorAngle="0" activated="0" exploded="0" flippedX="0" flippedY="0"/><Part partType="nosecone-1" id="143829" x="0.500000" y="14.500000" angle="4.712389" angleV="0.000000" editorAngle="3" activated="0" exploded="0" flippedX="0" flippedY="0"/><Part partType="nosecone-1" id="143830" x="0.500000" y="14.500000" angle="4.712389" angleV="0.000000" editorAngle="3" activated="0" exploded="0" flippedX="0" flippedY="0"/><Part partType="nosecone-1" id="143831" x="0.500000" y="14.500000" angle="4.712389" angleV="0.000000" editorAngle="3" activated="0" exploded="0" flippedX="0" flippedY="0"/><Part partType="nosecone-1" id="143834" x="-0.500000" y="14.500000" angle="1.570796" angleV="0.000000" editorAngle="1" activated="0" exploded="0" flippedX="0" flippedY="0"/><Part partType="nosecone-1" id="143832" x="-0.500000" y="14.500000" angle="1.570796" angleV="0.000000" editorAngle="1" activated="0" exploded="0" flippedX="0" flippedY="0"/><Part partType="nosecone-1" id="143835" x="-0.500000" y="14.500000" angle="1.570796" angleV="0.000000" editorAngle="1" activated="0" exploded="0" flippedX="0" flippedY="0"/><Part partType="nosecone-1" id="143833" x="1.000000" y="14.500000" angle="4.712389" angleV="0.000000" editorAngle="3" activated="0" exploded="0" flippedX="0" flippedY="0"/><Part partType="nosecone-1" id="143836" x="-1.000000" y="14.500000" angle="1.570796" angleV="0.000000" editorAngle="1" activated="0" exploded="0" flippedX="0" flippedY="0"/><Part partType="nosecone-1" id="143837" x="0.000000" y="14.500000" angle="0.000000" angleV="0.000000" editorAngle="0" activated="0" exploded="0" flippedX="0" flippedY="0"/><Part partType="nosecone-1" id="143838" x="0.000000" y="14.500000" angle="0.000000" angleV="0.000000" editorAngle="0" activated="0" exploded="0" flippedX="0" flippedY="0"/><Part partType="fueltank-0" id="1146087" x="0.000000" y="11.500000" angle="0.000000" angleV="0.000000" editorAngle="0"><Tank fuel="750.000000"/></Part><Part partType="engine-3" id="1146088" x="0.000000" y="9.000000" angle="0.000000" angleV="0.000000" editorAngle="0" activated="0" exploded="0" flippedX="0" flippedY="0"><Engine fuel="0.000000"/></Part><Part partType="detacher-1" id="1145991" x="0.000000" y="6.750000" angle="0.000000" angleV="0.000000" editorAngle="0" activated="0" exploded="0" flippedX="0" flippedY="0"/><Part partType="strut-1" id="1146006" x="0.000000" y="2.500000" angle="4.712389" angleV="0.000000" editorAngle="3" activated="0" exploded="0" flippedX="0" flippedY="0"/><Part partType="strut-1" id="1146008" x="0.000000" y="-5.500000" angle="4.712389" angleV="0.000000" editorAngle="3" activated="0" exploded="0" flippedX="0" flippedY="0"/><Part partType="strut-1" id="1146018" x="4.500000" y="-2.000000" angle="0.000000" angleV="0.000000" editorAngle="0" activated="0" exploded="0" flippedX="0" flippedY="0"/><Part partType="detacher-1" id="1146019" x="5.500000" y="-2.750000" angle="0.000000" angleV="0.000000" editorAngle="0" activated="0" exploded="0" flippedX="0" flippedY="0"/><Part partType="fueltank-0" id="1146020" x="5.500000" y="-3.500000" angle="0.000000" angleV="0.000000" editorAngle="0"><Tank fuel="750.000000"/></Part><Part partType="engine-3" id="1146021" x="5.500000" y="-6.000000" angle="0.000000" angleV="0.000000" editorAngle="0" activated="0" exploded="0" flippedX="0" flippedY="0"><Engine fuel="0.000000"/></Part><Part partType="engine-3" id="1146022" x="8.500000" y="-3.500000" angle="1.570796" angleV="0.000000" editorAngle="1" activated="0" exploded="0" flippedX="0" flippedY="0"><Engine fuel="0.000000"/></Part><Part partType="engine-3" id="1146023" x="2.500000" y="-3.500000" angle="4.712389" angleV="0.000000" editorAngle="3" activated="0" exploded="0" flippedX="0" flippedY="0"><Engine fuel="0.000000"/></Part><Part partType="strut-1" id="1146024" x="-4.500000" y="-2.000000" angle="0.000000" angleV="0.000000" editorAngle="0" activated="0" exploded="0" flippedX="0" flippedY="0"/><Part partType="detacher-1" id="1146025" x="-5.500000" y="-2.750000" angle="0.000000" angleV="0.000000" editorAngle="0" activated="0" exploded="0" flippedX="0" flippedY="0"/><Part partType="fueltank-0" id="1146026" x="-5.500000" y="-3.500000" angle="0.000000" angleV="0.000000" editorAngle="0"><Tank fuel="750.000000"/></Part><Part partType="engine-3" id="1146027" x="-5.500000" y="-6.000000" angle="0.000000" angleV="0.000000" editorAngle="0" activated="0" exploded="0" flippedX="0" flippedY="0"><Engine fuel="0.000000"/></Part><Part partType="engine-3" id="1146028" x="-8.500000" y="-3.500000" angle="4.712389" angleV="0.000000" editorAngle="3" activated="0" exploded="0" flippedX="0" flippedY="0"><Engine fuel="0.000000"/></Part><Part partType="engine-3" id="1146029" x="-2.500000" y="-3.500000" angle="1.570796" angleV="0.000000" editorAngle="1" activated="0" exploded="0" flippedX="0" flippedY="0"><Engine fuel="0.000000"/></Part><Part partType="strut-1" id="1146030" x="0.000000" y="-13.500000" angle="4.712389" angleV="0.000000" editorAngle="3" activated="0" exploded="0" flippedX="0" flippedY="0"/><Part partType="strut-1" id="1146031" x="0.000000" y="-21.500000" angle="4.712389" angleV="0.000000" editorAngle="3" activated="0" exploded="0" flippedX="0" flippedY="0"/><Part partType="strut-1" id="1146032" x="4.500000" y="-18.000000" angle="0.000000" angleV="0.000000" editorAngle="0" activated="0" exploded="0" flippedX="0" flippedY="0"/><Part partType="detacher-1" id="1146033" x="5.500000" y="-18.750000" angle="0.000000" angleV="0.000000" editorAngle="0" activated="0" exploded="0" flippedX="0" flippedY="0"/><Part partType="fueltank-0" id="1146034" x="5.500000" y="-19.500000" angle="0.000000" angleV="0.000000" editorAngle="0"><Tank fuel="750.000000"/></Part><Part partType="engine-3" id="1146035" x="5.500000" y="-22.000000" angle="0.000000" angleV="0.000000" editorAngle="0" activated="0" exploded="0" flippedX="0" flippedY="0"><Engine fuel="0.000000"/></Part><Part partType="engine-3" id="1146036" x="8.500000" y="-19.500000" angle="1.570796" angleV="0.000000" editorAngle="1" activated="0" exploded="0" flippedX="0" flippedY="0"><Engine fuel="0.000000"/></Part><Part partType="engine-3" id="1146037" x="2.500000" y="-19.500000" angle="4.712389" angleV="0.000000" editorAngle="3" activated="0" exploded="0" flippedX="0" flippedY="0"><Engine fuel="0.000000"/></Part><Part partType="strut-1" id="1146038" x="-4.500000" y="-18.000000" angle="0.000000" angleV="0.000000" editorAngle="0" activated="0" exploded="0" flippedX="0" flippedY="0"/><Part partType="detacher-1" id="1146039" x="-5.500000" y="-18.750000" angle="0.000000" angleV="0.000000" editorAngle="0" activated="0" exploded="0" flippedX="0" flippedY="0"/><Part partType="fueltank-0" id="1146040" x="-5.500000" y="-19.500000" angle="0.000000" angleV="0.000000" editorAngle="0"><Tank fuel="750.000000"/></Part><Part partType="engine-3" id="1146041" x="-5.500000" y="-22.000000" angle="0.000000" angleV="0.000000" editorAngle="0" activated="0" exploded="0" flippedX="0" flippedY="0"><Engine fuel="0.000000"/></Part><Part partType="engine-3" id="1146042" x="-8.500000" y="-19.500000" angle="4.712389" angleV="0.000000" editorAngle="3" activated="0" exploded="0" flippedX="0" flippedY="0"><Engine fuel="0.000000"/></Part><Part partType="engine-3" id="1146043" x="-2.500000" y="-19.500000" angle="1.570796" angleV="0.000000" editorAngle="1" activated="0" exploded="0" flippedX="0" flippedY="0"><Engine fuel="0.000000"/></Part><Part partType="strut-1" id="1146056" x="0.000000" y="-29.500000" angle="4.712389" angleV="0.000000" editorAngle="3" activated="0" exploded="0" flippedX="0" flippedY="0"/><Part partType="strut-1" id="1146044" x="-4.500000" y="-10.000000" angle="0.000000" angleV="0.000000" editorAngle="0" activated="0" exploded="0" flippedX="0" flippedY="0"/><Part partType="detacher-1" id="1146045" x="-5.500000" y="-10.750000" angle="0.000000" angleV="0.000000" editorAngle="0" activated="0" exploded="0" flippedX="0" flippedY="0"/><Part partType="fueltank-0" id="1146046" x="-5.500000" y="-11.500000" angle="0.000000" angleV="0.000000" editorAngle="0"><Tank fuel="750.000000"/></Part><Part partType="engine-3" id="1146047" x="-5.500000" y="-14.000000" angle="0.000000" angleV="0.000000" editorAngle="0" activated="0" exploded="0" flippedX="0" flippedY="0"><Engine fuel="0.000000"/></Part><Part partType="engine-3" id="1146048" x="-8.500000" y="-11.500000" angle="4.712389" angleV="0.000000" editorAngle="3" activated="0" exploded="0" flippedX="0" flippedY="0"><Engine fuel="0.000000"/></Part><Part partType="engine-3" id="1146049" x="-2.500000" y="-11.500000" angle="1.570796" angleV="0.000000" editorAngle="1" activated="0" exploded="0" flippedX="0" flippedY="0"><Engine fuel="0.000000"/></Part><Part partType="strut-1" id="1146050" x="4.500000" y="-10.000000" angle="0.000000" angleV="0.000000" editorAngle="0" activated="0" exploded="0" flippedX="0" flippedY="0"/><Part partType="detacher-1" id="1146051" x="5.500000" y="-10.750000" angle="0.000000" angleV="0.000000" editorAngle="0" activated="0" exploded="0" flippedX="0" flippedY="0"/><Part partType="fueltank-0" id="1146052" x="5.500000" y="-11.500000" angle="0.000000" angleV="0.000000" editorAngle="0"><Tank fuel="750.000000"/></Part><Part partType="engine-3" id="1146053" x="5.500000" y="-14.000000" angle="0.000000" angleV="0.000000" editorAngle="0" activated="0" exploded="0" flippedX="0" flippedY="0"><Engine fuel="0.000000"/></Part><Part partType="engine-3" id="1146054" x="8.500000" y="-11.500000" angle="1.570796" angleV="0.000000" editorAngle="1" activated="0" exploded="0" flippedX="0" flippedY="0"><Engine fuel="0.000000"/></Part><Part partType="engine-3" id="1146055" x="2.500000" y="-11.500000" angle="4.712389" angleV="0.000000" editorAngle="3" activated="0" exploded="0" flippedX="0" flippedY="0"><Engine fuel="0.000000"/></Part><Part partType="strut-1" id="1146011" x="-4.500000" y="6.000000" angle="0.000000" angleV="0.000000" editorAngle="0" activated="0" exploded="0" flippedX="0" flippedY="0"/><Part partType="detacher-1" id="1146012" x="-5.500000" y="5.250000" angle="0.000000" angleV="0.000000" editorAngle="0" activated="0" exploded="0" flippedX="0" flippedY="0"/><Part partType="fueltank-0" id="1146013" x="-5.500000" y="4.500000" angle="0.000000" angleV="0.000000" editorAngle="0"><Tank fuel="750.000000"/></Part><Part partType="engine-3" id="1146014" x="-5.500000" y="2.000000" angle="0.000000" angleV="0.000000" editorAngle="0" activated="0" exploded="0" flippedX="0" flippedY="0"><Engine fuel="0.000000"/></Part><Part partType="engine-3" id="1146015" x="-8.500000" y="4.500000" angle="4.712389" angleV="0.000000" editorAngle="3" activated="0" exploded="0" flippedX="0" flippedY="0"><Engine fuel="0.000000"/></Part><Part partType="engine-3" id="1146016" x="-2.500000" y="4.500000" angle="1.570796" angleV="0.000000" editorAngle="1" activated="0" exploded="0" flippedX="0" flippedY="0"><Engine fuel="0.000000"/></Part><Part partType="strut-1" id="1146059" x="-5.500000" y="7.000000" angle="0.000000" angleV="0.000000" editorAngle="0" activated="0" exploded="0" flippedX="0" flippedY="0"/><Part partType="strut-1" id="1146009" x="4.500000" y="6.000000" angle="0.000000" angleV="0.000000" editorAngle="0" activated="0" exploded="0" flippedX="0" flippedY="0"/><Part partType="detacher-1" id="1146010" x="5.500000" y="5.250000" angle="0.000000" angleV="0.000000" editorAngle="0" activated="0" exploded="0" flippedX="0" flippedY="0"/><Part partType="fueltank-0" id="1145992" x="5.500000" y="4.500000" angle="0.000000" angleV="0.000000" editorAngle="0"><Tank fuel="750.000000"/></Part><Part partType="engine-3" id="1145993" x="5.500000" y="2.000000" angle="0.000000" angleV="0.000000" editorAngle="0" activated="0" exploded="0" flippedX="0" flippedY="0"><Engine fuel="0.000000"/></Part><Part partType="engine-3" id="1145998" x="2.500000" y="4.500000" angle="4.712389" angleV="0.000000" editorAngle="3" activated="0" exploded="0" flippedX="0" flippedY="0"><Engine fuel="0.000000"/></Part><Part partType="engine-3" id="1145997" x="8.500000" y="4.500000" angle="1.570796" angleV="0.000000" editorAngle="1" activated="0" exploded="0" flippedX="0" flippedY="0"><Engine fuel="0.000000"/></Part><Part partType="strut-1" id="1146058" x="5.500000" y="7.000000" angle="0.000000" angleV="0.000000" editorAngle="0" activated="0" exploded="0" flippedX="0" flippedY="0"/><Part partType="fueltank-5" id="1146089" x="-1.250000" y="11.750000" angle="0.000000" angleV="0.000000" editorAngle="0"><Tank fuel="275.000000"/></Part><Part partType="fueltank-5" id="1146090" x="1.250000" y="11.750000" angle="0.000000" angleV="0.000000" editorAngle="0"><Tank fuel="275.000000"/></Part></Parts><Connections><Connection parentAttachPoint="1" childAttachPoint="2" parentPart="1" childPart="146732"/><Connection parentAttachPoint="1" childAttachPoint="1" parentPart="146732" childPart="143723"/><Connection parentAttachPoint="1" childAttachPoint="1" parentPart="143723" childPart="143728"/><Connection parentAttachPoint="1" childAttachPoint="1" parentPart="143723" childPart="143729"/><Connection parentAttachPoint="1" childAttachPoint="1" parentPart="143723" childPart="143732"/><Connection parentAttachPoint="1" childAttachPoint="2" parentPart="143723" childPart="143731"/><Connection parentAttachPoint="1" childAttachPoint="1" parentPart="143723" childPart="143733"/><Connection parentAttachPoint="1" childAttachPoint="1" parentPart="143723" childPart="143734"/><Connection parentAttachPoint="1" childAttachPoint="1" parentPart="143723" childPart="143738"/><Connection parentAttachPoint="1" childAttachPoint="1" parentPart="143723" childPart="143739"/><Connection parentAttachPoint="1" childAttachPoint="1" parentPart="143723" childPart="143740"/><Connection parentAttachPoint="1" childAttachPoint="1" parentPart="143723" childPart="143741"/><Connection parentAttachPoint="1" childAttachPoint="1" parentPart="143723" childPart="143742"/><Connection parentAttachPoint="1" childAttachPoint="1" parentPart="143723" childPart="143743"/><Connection parentAttachPoint="1" childAttachPoint="1" parentPart="143723" childPart="143744"/><Connection parentAttachPoint="1" childAttachPoint="1" parentPart="143723" childPart="143745"/><Connection parentAttachPoint="1" childAttachPoint="1" parentPart="143723" childPart="143746"/><Connection parentAttachPoint="1" childAttachPoint="1" parentPart="143723" childPart="143747"/><Connection parentAttachPoint="1" childAttachPoint="1" parentPart="143723" childPart="143748"/><Connection parentAttachPoint="1" childAttachPoint="1" parentPart="143723" childPart="143749"/><Connection parentAttachPoint="1" childAttachPoint="1" parentPart="143723" childPart="143783"/><Connection parentAttachPoint="1" childAttachPoint="1" parentPart="143723" childPart="143784"/><Connection parentAttachPoint="1" childAttachPoint="1" parentPart="143723" childPart="143785"/><Connection parentAttachPoint="1" childAttachPoint="1" parentPart="143723" childPart="143786"/><Connection parentAttachPoint="1" childAttachPoint="1" parentPart="143723" childPart="143787"/><Connection parentAttachPoint="1" childAttachPoint="1" parentPart="143723" childPart="143788"/><Connection parentAttachPoint="1" childAttachPoint="1" parentPart="143723" childPart="143789"/><Connection parentAttachPoint="1" childAttachPoint="1" parentPart="143723" childPart="143790"/><Connection parentAttachPoint="1" childAttachPoint="1" parentPart="143723" childPart="143791"/><Connection parentAttachPoint="1" childAttachPoint="1" parentPart="143723" childPart="143792"/><Connection parentAttachPoint="1" childAttachPoint="1" parentPart="143723" childPart="143793"/><Connection parentAttachPoint="1" childAttachPoint="1" parentPart="143723" childPart="143794"/><Connection parentAttachPoint="1" childAttachPoint="1" parentPart="143723" childPart="143795"/><Connection parentAttachPoint="1" childAttachPoint="1" parentPart="143723" childPart="143797"/><Connection parentAttachPoint="1" childAttachPoint="1" parentPart="143723" childPart="143796"/><Connection parentAttachPoint="1" childAttachPoint="1" parentPart="143723" childPart="143798"/><Connection parentAttachPoint="1" childAttachPoint="1" parentPart="143723" childPart="143799"/><Connection parentAttachPoint="1" childAttachPoint="1" parentPart="143723" childPart="143801"/><Connection parentAttachPoint="1" childAttachPoint="1" parentPart="143723" childPart="143802"/><Connection parentAttachPoint="1" childAttachPoint="1" parentPart="143723" childPart="143803"/><Connection parentAttachPoint="1" childAttachPoint="1" parentPart="143723" childPart="143804"/><Connection parentAttachPoint="1" childAttachPoint="1" parentPart="143723" childPart="143811"/><Connection parentAttachPoint="1" childAttachPoint="1" parentPart="143723" childPart="143812"/><Connection parentAttachPoint="1" childAttachPoint="1" parentPart="143723" childPart="143813"/><Connection parentAttachPoint="1" childAttachPoint="1" parentPart="143723" childPart="143814"/><Connection parentAttachPoint="1" childAttachPoint="1" parentPart="143723" childPart="143815"/><Connection parentAttachPoint="1" childAttachPoint="1" parentPart="143723" childPart="143816"/><Connection parentAttachPoint="1" childAttachPoint="1" parentPart="143723" childPart="143824"/><Connection parentAttachPoint="1" childAttachPoint="1" parentPart="143723" childPart="143818"/><Connection parentAttachPoint="1" childAttachPoint="1" parentPart="143723" childPart="143819"/><Connection parentAttachPoint="1" childAttachPoint="1" parentPart="143723" childPart="143820"/><Connection parentAttachPoint="1" childAttachPoint="1" parentPart="143723" childPart="143821"/><Connection parentAttachPoint="1" childAttachPoint="1" parentPart="143723" childPart="143822"/><Connection parentAttachPoint="1" childAttachPoint="1" parentPart="143723" childPart="143823"/><Connection parentAttachPoint="1" childAttachPoint="1" parentPart="143723" childPart="143826"/><Connection parentAttachPoint="1" childAttachPoint="1" parentPart="143723" childPart="143828"/><Connection parentAttachPoint="1" childAttachPoint="1" parentPart="143723" childPart="143829"/><Connection parentAttachPoint="1" childAttachPoint="1" parentPart="143723" childPart="143830"/><Connection parentAttachPoint="1" childAttachPoint="1" parentPart="143723" childPart="143831"/><Connection parentAttachPoint="1" childAttachPoint="1" parentPart="143723" childPart="143834"/><Connection parentAttachPoint="1" childAttachPoint="1" parentPart="143723" childPart="143832"/><Connection parentAttachPoint="1" childAttachPoint="1" parentPart="143723" childPart="143835"/><Connection parentAttachPoint="1" childAttachPoint="1" parentPart="143723" childPart="143833"/><Connection parentAttachPoint="1" childAttachPoint="1" parentPart="143723" childPart="143836"/><Connection parentAttachPoint="1" childAttachPoint="1" parentPart="143723" childPart="143837"/><Connection parentAttachPoint="1" childAttachPoint="1" parentPart="143723" childPart="143838"/><Connection parentAttachPoint="2" childAttachPoint="1" parentPart="1" childPart="1146087"/><Connection parentAttachPoint="2" childAttachPoint="1" parentPart="1146087" childPart="1146088"/><Connection parentAttachPoint="2" childAttachPoint="1" parentPart="1146088" childPart="1145991"/><Connection parentAttachPoint="2" childAttachPoint="3" parentPart="1145991" childPart="1146006"/><Connection parentAttachPoint="4" childAttachPoint="3" parentPart="1146006" childPart="1146008"/><Connection parentAttachPoint="1" childAttachPoint="3" parentPart="1146008" childPart="1146018"/><Connection parentAttachPoint="2" childAttachPoint="1" parentPart="1146018" childPart="1146019"/><Connection parentAttachPoint="2" childAttachPoint="1" parentPart="1146019" childPart="1146020"/><Connection parentAttachPoint="2" childAttachPoint="1" parentPart="1146020" childPart="1146021"/><Connection parentAttachPoint="4" childAttachPoint="1" parentPart="1146020" childPart="1146022"/><Connection parentAttachPoint="3" childAttachPoint="1" parentPart="1146020" childPart="1146023"/><Connection parentAttachPoint="2" childAttachPoint="4" parentPart="1146008" childPart="1146024"/><Connection parentAttachPoint="2" childAttachPoint="1" parentPart="1146024" childPart="1146025"/><Connection parentAttachPoint="2" childAttachPoint="1" parentPart="1146025" childPart="1146026"/><Connection parentAttachPoint="2" childAttachPoint="1" parentPart="1146026" childPart="1146027"/><Connection parentAttachPoint="3" childAttachPoint="1" parentPart="1146026" childPart="1146028"/><Connection parentAttachPoint="4" childAttachPoint="1" parentPart="1146026" childPart="1146029"/><Connection parentAttachPoint="4" childAttachPoint="3" parentPart="1146008" childPart="1146030"/><Connection parentAttachPoint="4" childAttachPoint="3" parentPart="1146030" childPart="1146031"/><Connection parentAttachPoint="1" childAttachPoint="3" parentPart="1146031" childPart="1146032"/><Connection parentAttachPoint="2" childAttachPoint="1" parentPart="1146032" childPart="1146033"/><Connection parentAttachPoint="2" childAttachPoint="1" parentPart="1146033" childPart="1146034"/><Connection parentAttachPoint="2" childAttachPoint="1" parentPart="1146034" childPart="1146035"/><Connection parentAttachPoint="4" childAttachPoint="1" parentPart="1146034" childPart="1146036"/><Connection parentAttachPoint="3" childAttachPoint="1" parentPart="1146034" childPart="1146037"/><Connection parentAttachPoint="2" childAttachPoint="4" parentPart="1146031" childPart="1146038"/><Connection parentAttachPoint="2" childAttachPoint="1" parentPart="1146038" childPart="1146039"/><Connection parentAttachPoint="2" childAttachPoint="1" parentPart="1146039" childPart="1146040"/><Connection parentAttachPoint="2" childAttachPoint="1" parentPart="1146040" childPart="1146041"/><Connection parentAttachPoint="3" childAttachPoint="1" parentPart="1146040" childPart="1146042"/><Connection parentAttachPoint="4" childAttachPoint="1" parentPart="1146040" childPart="1146043"/><Connection parentAttachPoint="4" childAttachPoint="3" parentPart="1146031" childPart="1146056"/><Connection parentAttachPoint="2" childAttachPoint="4" parentPart="1146030" childPart="1146044"/><Connection parentAttachPoint="2" childAttachPoint="1" parentPart="1146044" childPart="1146045"/><Connection parentAttachPoint="2" childAttachPoint="1" parentPart="1146045" childPart="1146046"/><Connection parentAttachPoint="2" childAttachPoint="1" parentPart="1146046" childPart="1146047"/><Connection parentAttachPoint="3" childAttachPoint="1" parentPart="1146046" childPart="1146048"/><Connection parentAttachPoint="4" childAttachPoint="1" parentPart="1146046" childPart="1146049"/><Connection parentAttachPoint="1" childAttachPoint="3" parentPart="1146030" childPart="1146050"/><Connection parentAttachPoint="2" childAttachPoint="1" parentPart="1146050" childPart="1146051"/><Connection parentAttachPoint="2" childAttachPoint="1" parentPart="1146051" childPart="1146052"/><Connection parentAttachPoint="2" childAttachPoint="1" parentPart="1146052" childPart="1146053"/><Connection parentAttachPoint="4" childAttachPoint="1" parentPart="1146052" childPart="1146054"/><Connection parentAttachPoint="3" childAttachPoint="1" parentPart="1146052" childPart="1146055"/><Connection parentAttachPoint="2" childAttachPoint="4" parentPart="1146006" childPart="1146011"/><Connection parentAttachPoint="2" childAttachPoint="1" parentPart="1146011" childPart="1146012"/><Connection parentAttachPoint="2" childAttachPoint="1" parentPart="1146012" childPart="1146013"/><Connection parentAttachPoint="2" childAttachPoint="1" parentPart="1146013" childPart="1146014"/><Connection parentAttachPoint="3" childAttachPoint="1" parentPart="1146013" childPart="1146015"/><Connection parentAttachPoint="4" childAttachPoint="1" parentPart="1146013" childPart="1146016"/><Connection parentAttachPoint="1" childAttachPoint="2" parentPart="1146011" childPart="1146059"/><Connection parentAttachPoint="1" childAttachPoint="3" parentPart="1146006" childPart="1146009"/><Connection parentAttachPoint="2" childAttachPoint="1" parentPart="1146009" childPart="1146010"/><Connection parentAttachPoint="2" childAttachPoint="1" parentPart="1146010" childPart="1145992"/><Connection parentAttachPoint="2" childAttachPoint="1" parentPart="1145992" childPart="1145993"/><Connection parentAttachPoint="3" childAttachPoint="1" parentPart="1145992" childPart="1145998"/><Connection parentAttachPoint="4" childAttachPoint="1" parentPart="1145992" childPart="1145997"/><Connection parentAttachPoint="1" childAttachPoint="2" parentPart="1146009" childPart="1146058"/><Connection parentAttachPoint="3" childAttachPoint="1" parentPart="1146087" childPart="1146089"/><Connection parentAttachPoint="4" childAttachPoint="2" parentPart="1146087" childPart="1146090"/></Connections></Ship>