<Ship version="1" liftedOff="0" touchingGround="0"><DisconnectedParts><DisconnectedPart><Parts><Part partType="detacher-1" id="1145170" x="0.00000" y="-17.750000" angle="0.000000" angleV="0.000000" editorAngle="0" activated="0" exploded="0" flippedX="0" flippedY="0"/><Part partType="dock-1" id="1145171" x="0.00000" y="-17.250000" angle="0.000000" angleV="0.000000" editorAngle="0" activated="0" exploded="0" flippedX="0" flippedY="0"/><Part partType="fueltank-3" id="1145172" x="6.500000" y="6.500000" angle="0.000000" angleV="0.000000" editorAngle="0"><Tank fuel="6000.000000"/></Part><Part partType="strut-1" id="1145175" x="6.500000" y="11.000000" angle="0.000000" angleV="0.000000" editorAngle="0" activated="0" exploded="0" flippedX="0" flippedY="0"/><Part partType="pod-1" id="1145183" x="6.500000" y="12.250000" angle="0.000000" angleV="0.000000" editorAngle="0"><Pod throttle="0.000000" name=""><Staging currentStage="0"/></Pod></Part><Part partType="strut-1" id="1145225" x="2.000000" y="7.500000" angle="4.712389" angleV="0.000000" editorAngle="3" activated="0" exploded="0" flippedX="0" flippedY="0"/><Part partType="strut-1" id="1145226" x="11.000000" y="7.500000" angle="4.712389" angleV="0.000000" editorAngle="3" activated="0" exploded="0" flippedX="0" flippedY="0"/><Part partType="fueltank-1" id="1145194" x="8.500000" y="9.500000" angle="1.570796" angleV="0.000000" editorAngle="1"><Tank fuel="1500.000000"/></Part><Part partType="engine-2" id="1145195" x="8.500000" y="7.000000" angle="0.000000" angleV="0.000000" editorAngle="0" activated="0" exploded="0" flippedX="0" flippedY="0"><Engine fuel="0.000000"/></Part><Part partType="fueltank-1" id="1145196" x="4.500000" y="9.500000" angle="4.712389" angleV="0.000000" editorAngle="3"><Tank fuel="1500.000000"/></Part><Part partType="engine-2" id="1145197" x="4.500000" y="7.000000" angle="0.000000" angleV="0.000000" editorAngle="0" activated="0" exploded="0" flippedX="0" flippedY="0"><Engine fuel="0.000000"/></Part></Parts><Connections><Connection parentAttachPoint="1" childAttachPoint="1" parentPart="1145170" childPart="1145171"/><DockConnection dockPart="1145171" parentPart="1145171" childPart="1145172"/><Connection parentAttachPoint="4" childAttachPoint="1" parentPart="1145172" childPart="1145175"/><Connection parentAttachPoint="1" childAttachPoint="2" parentPart="1145175" childPart="1145183"/><Connection parentAttachPoint="3" childAttachPoint="1" parentPart="1145175" childPart="1145225"/><Connection parentAttachPoint="4" childAttachPoint="2" parentPart="1145175" childPart="1145226"/><Connection parentAttachPoint="4" childAttachPoint="1" parentPart="1145172" childPart="1145194"/><Connection parentAttachPoint="3" childAttachPoint="1" parentPart="1145194" childPart="1145195"/><Connection parentAttachPoint="3" childAttachPoint="1" parentPart="1145172" childPart="1145196"/><Connection parentAttachPoint="4" childAttachPoint="1" parentPart="1145196" childPart="1145197"/></Connections></DisconnectedPart><DisconnectedPart><Parts><Part partType="detacher-1" id="1145228" x="-0.00000" y="-17.750000" angle="0.000000" angleV="0.000000" editorAngle="0" activated="0" exploded="0" flippedX="0" flippedY="0"/><Part partType="dock-1" id="1145229" x="-0.00000" y="-17.250000" angle="0.000000" angleV="0.000000" editorAngle="0" activated="0" exploded="0" flippedX="0" flippedY="0"/><Part partType="fueltank-3" id="1145230" x="-6.500000" y="6.500000" angle="0.000000" angleV="0.000000" editorAngle="0"><Tank fuel="6000.000000"/></Part><Part partType="strut-1" id="1145231" x="-6.500000" y="11.000000" angle="0.000000" angleV="0.000000" editorAngle="0" activated="0" exploded="0" flippedX="0" flippedY="0"/><Part partType="pod-1" id="1145232" x="-6.500000" y="12.250000" angle="0.000000" angleV="0.000000" editorAngle="0"><Pod throttle="0.000000" name=""><Staging currentStage="0"/></Pod></Part><Part partType="strut-1" id="1145233" x="-11.000000" y="7.500000" angle="4.712389" angleV="0.000000" editorAngle="3" activated="0" exploded="0" flippedX="0" flippedY="0"/><Part partType="strut-1" id="1145234" x="-2.000000" y="7.500000" angle="4.712389" angleV="0.000000" editorAngle="3" activated="0" exploded="0" flippedX="0" flippedY="0"/><Part partType="fueltank-1" id="1145235" x="-4.500000" y="9.500000" angle="1.570796" angleV="0.000000" editorAngle="1"><Tank fuel="1500.000000"/></Part><Part partType="engine-2" id="1145236" x="-4.500000" y="7.000000" angle="0.000000" angleV="0.000000" editorAngle="0" activated="0" exploded="0" flippedX="0" flippedY="0"><Engine fuel="0.000000"/></Part><Part partType="fueltank-1" id="1145237" x="-8.500000" y="9.500000" angle="4.712389" angleV="0.000000" editorAngle="3"><Tank fuel="1500.000000"/></Part><Part partType="engine-2" id="1145238" x="-8.500000" y="7.000000" angle="0.000000" angleV="0.000000" editorAngle="0" activated="0" exploded="0" flippedX="0" flippedY="0"><Engine fuel="0.000000"/></Part></Parts><Connections><Connection parentAttachPoint="1" childAttachPoint="1" parentPart="1145228" childPart="1145229"/><DockConnection dockPart="1145229" parentPart="1145229" childPart="1145230"/><Connection parentAttachPoint="4" childAttachPoint="1" parentPart="1145230" childPart="1145231"/><Connection parentAttachPoint="1" childAttachPoint="2" parentPart="1145231" childPart="1145232"/><Connection parentAttachPoint="3" childAttachPoint="1" parentPart="1145231" childPart="1145233"/><Connection parentAttachPoint="4" childAttachPoint="2" parentPart="1145231" childPart="1145234"/><Connection parentAttachPoint="4" childAttachPoint="1" parentPart="1145230" childPart="1145235"/><Connection parentAttachPoint="3" childAttachPoint="1" parentPart="1145235" childPart="1145236"/><Connection parentAttachPoint="3" childAttachPoint="1" parentPart="1145230" childPart="1145237"/><Connection parentAttachPoint="4" childAttachPoint="1" parentPart="1145237" childPart="1145238"/></Connections></DisconnectedPart></DisconnectedParts><Parts><Part partType="pod-1" id="1" x="0.000000" y="-18.750000" angle="0.000000" angleV="0.000000" editorAngle="0"><Pod throttle="0.000000" name=""><Staging currentStage="0"><Step><Activate Id="1145199" moved="1"/><Activate Id="1145205" moved="1"/></Step></Staging></Pod></Part><Part partType="strut-1" id="1145192" x="0.000000" y="-20.000000" angle="0.000000" angleV="0.000000" editorAngle="0" activated="0" exploded="0" flippedX="0" flippedY="0"/><Part partType="fueltank-3" id="1145193" x="0.000000" y="-24.500000" angle="0.000000" angleV="0.000000" editorAngle="0"><Tank fuel="6000.000000"/></Part><Part partType="fueltank-1" id="1145198" x="2.000000" y="-21.500000" angle="1.570796" angleV="0.000000" editorAngle="1"><Tank fuel="1500.000000"/></Part><Part partType="engine-2" id="1145199" x="2.000000" y="-24.000000" angle="0.000000" angleV="0.000000" editorAngle="0" activated="0" exploded="0" flippedX="0" flippedY="0"><Engine fuel="0.000000"/></Part><Part partType="fueltank-1" id="1145204" x="-2.000000" y="-21.500000" angle="4.712389" angleV="0.000000" editorAngle="3"><Tank fuel="1500.000000"/></Part><Part partType="engine-2" id="1145205" x="-2.000000" y="-24.000000" angle="0.000000" angleV="0.000000" editorAngle="0" activated="0" exploded="0" flippedX="0" flippedY="0"><Engine fuel="0.000000"/></Part></Parts><Connections><Connection parentAttachPoint="2" childAttachPoint="1" parentPart="1" childPart="1145192"/><Connection parentAttachPoint="2" childAttachPoint="1" parentPart="1145192" childPart="1145193"/><Connection parentAttachPoint="4" childAttachPoint="1" parentPart="1145193" childPart="1145198"/><Connection parentAttachPoint="3" childAttachPoint="1" parentPart="1145198" childPart="1145199"/><Connection parentAttachPoint="3" childAttachPoint="1" parentPart="1145193" childPart="1145204"/><Connection parentAttachPoint="4" childAttachPoint="1" parentPart="1145204" childPart="1145205"/></Connections></Ship>