<Ship version="1" liftedOff="0" touchingGround="0"><DisconnectedParts><DisconnectedPart><Parts><Part partType="lander-1" id="171757" x="-22.750000" y="20.250000" angle="0.000000" angleV="0.000000" editorAngle="0" activated="0" exploded="0" flippedX="0" flippedY="0" lower="0" raise="0" length="2.260000" legAngle="0.000000"/></Parts><Connections/></DisconnectedPart><DisconnectedPart><Parts><Part partType="dock-1" id="171787" x="0.500000" y="19.250000" angle="0.000000" angleV="0.000000" editorAngle="0" activated="0" exploded="0" flippedX="0" flippedY="0"/></Parts><Connections/></DisconnectedPart><DisconnectedPart><Parts><Part partType="nosecone-1" id="174348" x="23.500000" y="8.500000" angle="4.712389" angleV="0.000000" editorAngle="3" activated="0" exploded="0" flippedX="0" flippedY="0"/></Parts><Connections/></DisconnectedPart><DisconnectedPart><Parts><Part partType="rcs-1" id="174405" x="26.750000" y="10.750000" angle="4.712389" angleV="0.000000" editorAngle="3" activated="0" exploded="0" flippedX="0" flippedY="0"/></Parts><Connections/></DisconnectedPart><DisconnectedPart><Parts><Part partType="detacher-1" id="174390" x="33.500000" y="41.750000" angle="0.000000" angleV="0.000000" editorAngle="0" activated="0" exploded="0" flippedX="0" flippedY="0"/><Part partType="fueltank-0" id="174391" x="33.500000" y="42.500000" angle="0.000000" angleV="0.000000" editorAngle="0"><Tank fuel="750.000000"/></Part><Part partType="wheel-2" id="172593" x="33.500000" y="43.000000" angle="0.000000" angleV="0.000000" editorAngle="0" activated="0" exploded="0" flippedX="0" flippedY="0"/><Part partType="fueltank-0" id="174396" x="32.000000" y="42.500000" angle="4.712389" angleV="0.000000" editorAngle="3"><Tank fuel="750.000000"/></Part><Part partType="engine-3" id="174397" x="29.500000" y="42.500000" angle="4.712389" angleV="0.000000" editorAngle="3" activated="0" exploded="0" flippedX="0" flippedY="0"><Engine fuel="0.000000"/></Part><Part partType="wheel-2" id="174408" x="27.500000" y="42.500000" angle="0.000000" angleV="0.000000" editorAngle="0" activated="0" exploded="0" flippedX="0" flippedY="0"/><Part partType="strut-1" id="174392" x="38.500000" y="42.500000" angle="0.000000" angleV="0.000000" editorAngle="0" activated="0" exploded="0" flippedX="0" flippedY="0"/><Part partType="battery-0" id="174399" x="41.500000" y="41.750000" angle="0.000000" angleV="0.000000" editorAngle="0"><Tank fuel="250.000000"/></Part><Part partType="wheel-2" id="171769" x="41.500000" y="41.500000" angle="0.000000" angleV="0.000000" editorAngle="0" activated="0" exploded="0" flippedX="0" flippedY="0"/><Part partType="rcs-1" id="174400" x="42.750000" y="42.750000" angle="0.000000" angleV="0.000000" editorAngle="0" activated="0" exploded="0" flippedX="0" flippedY="0"/><Part partType="rcs-1" id="174401" x="41.750000" y="43.250000" angle="4.712389" angleV="0.000000" editorAngle="3" activated="0" exploded="0" flippedX="1" flippedY="0"/><Part partType="rcs-1" id="174402" x="40.250000" y="43.250000" angle="4.712389" angleV="0.000000" editorAngle="3" activated="0" exploded="0" flippedX="1" flippedY="0"/><Part partType="rcs-1" id="174403" x="38.750000" y="43.250000" angle="4.712389" angleV="0.000000" editorAngle="3" activated="0" exploded="0" flippedX="1" flippedY="0"/><Part partType="rcs-1" id="174404" x="37.250000" y="43.250000" angle="4.712389" angleV="0.000000" editorAngle="3" activated="0" exploded="0" flippedX="1" flippedY="0"/><Part partType="wheel-2" id="174407" x="36.000000" y="42.000000" angle="0.000000" angleV="0.000000" editorAngle="0" activated="0" exploded="0" flippedX="0" flippedY="0"/><Part partType="fueltank-5" id="174409" x="35.750000" y="43.250000" angle="4.712389" angleV="0.000000" editorAngle="3"><Tank fuel="275.000000"/></Part></Parts><Connections><Connection parentAttachPoint="1" childAttachPoint="2" parentPart="174390" childPart="174391"/><Connection parentAttachPoint="1" childAttachPoint="1" parentPart="174391" childPart="172593"/><Connection parentAttachPoint="3" childAttachPoint="1" parentPart="174391" childPart="174396"/><Connection parentAttachPoint="2" childAttachPoint="1" parentPart="174396" childPart="174397"/><Connection parentAttachPoint="2" childAttachPoint="1" parentPart="174397" childPart="174408"/><Connection parentAttachPoint="4" childAttachPoint="3" parentPart="174391" childPart="174392"/><Connection parentAttachPoint="2" childAttachPoint="1" parentPart="174392" childPart="174399"/><Connection parentAttachPoint="2" childAttachPoint="1" parentPart="174399" childPart="171769"/><Connection parentAttachPoint="4" childAttachPoint="2" parentPart="174392" childPart="174400"/><Connection parentAttachPoint="1" childAttachPoint="1" parentPart="174392" childPart="174401"/><Connection parentAttachPoint="1" childAttachPoint="1" parentPart="174392" childPart="174402"/><Connection parentAttachPoint="1" childAttachPoint="1" parentPart="174392" childPart="174403"/><Connection parentAttachPoint="1" childAttachPoint="1" parentPart="174392" childPart="174404"/><Connection parentAttachPoint="2" childAttachPoint="1" parentPart="174392" childPart="174407"/><Connection parentAttachPoint="1" childAttachPoint="1" parentPart="174392" childPart="174409"/></Connections></DisconnectedPart><DisconnectedPart><Parts><Part partType="parachute-1" id="171760" x="-26.250000" y="30.500000" angle="1.570796" angleV="0.000000" editorAngle="1" activated="0" exploded="0" flippedX="0" flippedY="0" chuteX="-26.250000" chuteY="30.500000" chuteAngle="0.000000" chuteHeight="0.000000" inflation="0.100000" inflate="0" deployed="0" rope="0"/></Parts><Connections/></DisconnectedPart><DisconnectedPart><Parts><Part partType="engine-1" id="171654" x="20.000000" y="29.000000" angle="4.712389" angleV="0.000000" editorAngle="3" activated="0" exploded="0" flippedX="0" flippedY="0"><Engine fuel="0.000000"/></Part></Parts><Connections/></DisconnectedPart><DisconnectedPart><Parts><Part partType="strut-1" id="171696" x="-27.000000" y="33.000000" angle="0.000000" angleV="0.000000" editorAngle="0" activated="0" exploded="0" flippedX="0" flippedY="0"/></Parts><Connections/></DisconnectedPart><DisconnectedPart><Parts><Part partType="parachute-1" id="171729" x="-24.000000" y="39.250000" angle="0.000000" angleV="0.000000" editorAngle="0" activated="0" exploded="0" flippedX="0" flippedY="0" chuteX="-24.000000" chuteY="39.250000" chuteAngle="0.000000" chuteHeight="0.000000" inflation="0.100000" inflate="0" deployed="0" rope="0"/></Parts><Connections/></DisconnectedPart><DisconnectedPart><Parts><Part partType="lander-1" id="174421" x="-14.250000" y="30.750000" angle="3.141593" angleV="0.000000" editorAngle="2" activated="0" exploded="0" flippedX="0" flippedY="0" lower="0" raise="0" length="2.260000" legAngle="0.000000"/></Parts><Connections/></DisconnectedPart><DisconnectedPart><Parts><Part partType="parachute-1" id="174412" x="4.250000" y="28.000000" angle="4.712389" angleV="0.000000" editorAngle="3" activated="0" exploded="0" flippedX="0" flippedY="0" chuteX="4.250000" chuteY="28.000000" chuteAngle="0.000000" chuteHeight="0.000000" inflation="0.100000" inflate="0" deployed="0" rope="0"/></Parts><Connections/></DisconnectedPart><DisconnectedPart><Parts><Part partType="wheel-2" id="171718" x="25.500000" y="9.000000" angle="0.000000" angleV="0.000000" editorAngle="0" activated="0" exploded="0" flippedX="0" flippedY="0"/></Parts><Connections/></DisconnectedPart><DisconnectedPart><Parts><Part partType="solar-1" id="174449" x="5.250000" y="16.500000" angle="0.000000" angleV="0.000000" editorAngle="0" activated="0" exploded="0" flippedX="0" flippedY="0" extension="0.000000"/></Parts><Connections/></DisconnectedPart><DisconnectedPart><Parts><Part partType="fueltank-5" id="174452" x="-9.250000" y="9.250000" angle="0.000000" angleV="0.000000" editorAngle="0"><Tank fuel="275.000000"/></Part></Parts><Connections/></DisconnectedPart><DisconnectedPart><Parts><Part partType="fueltank-5" id="174453" x="-33.250000" y="-6.250000" angle="0.000000" angleV="0.000000" editorAngle="0"><Tank fuel="275.000000"/></Part></Parts><Connections/></DisconnectedPart><DisconnectedPart><Parts><Part partType="fueltank-5" id="174454" x="-35.250000" y="22.250000" angle="0.000000" angleV="0.000000" editorAngle="0"><Tank fuel="275.000000"/></Part></Parts><Connections/></DisconnectedPart><DisconnectedPart><Parts><Part partType="fueltank-5" id="174455" x="-12.750000" y="15.750000" angle="0.000000" angleV="0.000000" editorAngle="0"><Tank fuel="275.000000"/></Part></Parts><Connections/></DisconnectedPart><DisconnectedPart><Parts><Part partType="fueltank-5" id="174457" x="-34.250000" y="16.750000" angle="0.000000" angleV="0.000000" editorAngle="0"><Tank fuel="275.000000"/></Part></Parts><Connections/></DisconnectedPart><DisconnectedPart><Parts><Part partType="fueltank-5" id="174458" x="-33.250000" y="-2.750000" angle="0.000000" angleV="0.000000" editorAngle="0"><Tank fuel="275.000000"/></Part></Parts><Connections/></DisconnectedPart><DisconnectedPart><Parts><Part partType="fueltank-5" id="174459" x="-33.250000" y="-2.750000" angle="3.141593" angleV="0.000000" editorAngle="2"><Tank fuel="275.000000"/></Part></Parts><Connections/></DisconnectedPart><DisconnectedPart><Parts><Part partType="parachute-1" id="172605" x="9.750000" y="19.500000" angle="4.712389" angleV="0.000000" editorAngle="3" activated="0" exploded="0" flippedX="0" flippedY="0" chuteX="9.750000" chuteY="19.500000" chuteAngle="0.000000" chuteHeight="0.000000" inflation="0.100000" inflate="0" deployed="0" rope="0"/></Parts><Connections/></DisconnectedPart><DisconnectedPart><Parts><Part partType="strut-1" id="171672" x="34.000000" y="17.000000" angle="0.000000" angleV="0.000000" editorAngle="0" activated="0" exploded="0" flippedX="0" flippedY="0"/></Parts><Connections/></DisconnectedPart><DisconnectedPart><Parts><Part partType="detacher-1" id="174486" x="9.250000" y="4.500000" angle="4.712389" angleV="0.000000" editorAngle="3" activated="0" exploded="0" flippedX="0" flippedY="0"/></Parts><Connections/></DisconnectedPart><DisconnectedPart><Parts><Part partType="parachute-1" id="174635" x="0.500000" y="13.250000" angle="0.000000" angleV="0.000000" editorAngle="0" activated="0" exploded="0" flippedX="0" flippedY="0" chuteX="0.500000" chuteY="13.250000" chuteAngle="0.000000" chuteHeight="0.000000" inflation="0.100000" inflate="0" deployed="0" rope="0"/></Parts><Connections/></DisconnectedPart><DisconnectedPart><Parts><Part partType="parachute-1" id="174637" x="-8.000000" y="12.750000" angle="3.141593" angleV="0.000000" editorAngle="2" activated="0" exploded="0" flippedX="0" flippedY="0" chuteX="-8.000000" chuteY="12.750000" chuteAngle="0.000000" chuteHeight="0.000000" inflation="0.100000" inflate="0" deployed="0" rope="0"/></Parts><Connections/></DisconnectedPart><DisconnectedPart><Parts><Part partType="solar-1" id="174631" x="-3.500000" y="-11.250000" angle="1.570796" angleV="0.000000" editorAngle="1" activated="0" exploded="0" flippedX="0" flippedY="0" extension="0.000000"/></Parts><Connections/></DisconnectedPart><DisconnectedPart><Parts><Part partType="parachute-1" id="174651" x="-12.250000" y="3.000000" angle="1.570796" angleV="0.000000" editorAngle="1" activated="0" exploded="0" flippedX="0" flippedY="0" chuteX="-12.250000" chuteY="3.000000" chuteAngle="0.000000" chuteHeight="0.000000" inflation="0.100000" inflate="0" deployed="0" rope="0"/></Parts><Connections/></DisconnectedPart><DisconnectedPart><Parts><Part partType="parachute-1" id="174652" x="-10.750000" y="-0.500000" angle="1.570796" angleV="0.000000" editorAngle="1" activated="0" exploded="0" flippedX="0" flippedY="0" chuteX="-10.750000" chuteY="-0.500000" chuteAngle="0.000000" chuteHeight="0.000000" inflation="0.100000" inflate="0" deployed="0" rope="0"/></Parts><Connections/></DisconnectedPart><DisconnectedPart><Parts><Part partType="detacher-1" id="174655" x="-17.000000" y="10.250000" angle="3.141593" angleV="0.000000" editorAngle="2" activated="0" exploded="0" flippedX="0" flippedY="0"/><Part partType="parachute-1" id="174654" x="-17.000000" y="10.750000" angle="0.000000" angleV="0.000000" editorAngle="0" activated="0" exploded="0" flippedX="0" flippedY="0" chuteX="-17.000000" chuteY="10.750000" chuteAngle="0.000000" chuteHeight="0.000000" inflation="0.100000" inflate="0" deployed="0" rope="0"/></Parts><Connections><Connection parentAttachPoint="2" childAttachPoint="1" parentPart="174655" childPart="174654"/></Connections></DisconnectedPart><DisconnectedPart><Parts><Part partType="lander-1" id="174644" x="-15.750000" y="1.250000" angle="4.712389" angleV="0.000000" editorAngle="3" activated="0" exploded="0" flippedX="0" flippedY="0" lower="0" raise="0" length="2.260000" legAngle="0.000000"/></Parts><Connections/></DisconnectedPart><DisconnectedPart><Parts><Part partType="lander-1" id="174647" x="-10.750000" y="0.250000" angle="3.141593" angleV="0.000000" editorAngle="2" activated="0" exploded="0" flippedX="0" flippedY="0" lower="0" raise="0" length="2.260000" legAngle="0.000000"/></Parts><Connections/></DisconnectedPart><DisconnectedPart><Parts><Part partType="wheel-2" id="171723" x="6.500000" y="-12.000000" angle="0.000000" angleV="0.000000" editorAngle="0" activated="0" exploded="0" flippedX="0" flippedY="0"/></Parts><Connections/></DisconnectedPart><DisconnectedPart><Parts><Part partType="detacher-1" id="174759" x="-17.500000" y="6.750000" angle="0.000000" angleV="0.000000" editorAngle="0" activated="0" exploded="0" flippedX="0" flippedY="0"/></Parts><Connections/></DisconnectedPart><DisconnectedPart><Parts><Part partType="parachute-1" id="174751" x="-21.250000" y="15.500000" angle="1.570796" angleV="0.000000" editorAngle="1" activated="0" exploded="0" flippedX="0" flippedY="0" chuteX="-21.250000" chuteY="15.500000" chuteAngle="0.000000" chuteHeight="0.000000" inflation="0.100000" inflate="0" deployed="0" rope="0"/></Parts><Connections/></DisconnectedPart><DisconnectedPart><Parts><Part partType="parachute-1" id="172599" x="-15.250000" y="14.000000" angle="1.570796" angleV="0.000000" editorAngle="1" activated="0" exploded="0" flippedX="0" flippedY="0" chuteX="-15.250000" chuteY="14.000000" chuteAngle="0.000000" chuteHeight="0.000000" inflation="0.100000" inflate="0" deployed="0" rope="0"/></Parts><Connections/></DisconnectedPart><DisconnectedPart><Parts><Part partType="parachute-1" id="174762" x="-9.750000" y="11.500000" angle="1.570796" angleV="0.000000" editorAngle="1" activated="0" exploded="0" flippedX="0" flippedY="0" chuteX="-9.750000" chuteY="11.500000" chuteAngle="0.000000" chuteHeight="0.000000" inflation="0.100000" inflate="0" deployed="0" rope="0"/></Parts><Connections/></DisconnectedPart><DisconnectedPart><Parts><Part partType="detacher-1" id="174763" x="-11.250000" y="10.500000" angle="4.712389" angleV="0.000000" editorAngle="3" activated="0" exploded="0" flippedX="0" flippedY="0"/></Parts><Connections/></DisconnectedPart><DisconnectedPart><Parts><Part partType="lander-1" id="174479" x="-26.250000" y="11.250000" angle="4.712389" angleV="0.000000" editorAngle="3" activated="0" exploded="0" flippedX="0" flippedY="0" lower="0" raise="0" length="2.260000" legAngle="0.000000"/></Parts><Connections/></DisconnectedPart><DisconnectedPart><Parts><Part partType="parachute-1" id="174482" x="-14.500000" y="11.750000" angle="0.000000" angleV="0.000000" editorAngle="0" activated="0" exploded="0" flippedX="0" flippedY="0" chuteX="-14.500000" chuteY="11.750000" chuteAngle="0.000000" chuteHeight="0.000000" inflation="0.100000" inflate="0" deployed="0" rope="0"/></Parts><Connections/></DisconnectedPart><DisconnectedPart><Parts><Part partType="detacher-1" id="174439" x="-13.000000" y="13.250000" angle="0.000000" angleV="0.000000" editorAngle="0" activated="0" exploded="0" flippedX="0" flippedY="0"/></Parts><Connections/></DisconnectedPart><DisconnectedPart><Parts><Part partType="fuselage-1" id="174774" x="-7.500000" y="3.000000" angle="0.000000" angleV="0.000000" editorAngle="0" activated="0" exploded="0" flippedX="0" flippedY="0"/></Parts><Connections/></DisconnectedPart><DisconnectedPart><Parts><Part partType="fueltank-5" id="174775" x="1.250000" y="13.750000" angle="0.000000" angleV="0.000000" editorAngle="0"><Tank fuel="275.000000"/></Part></Parts><Connections/></DisconnectedPart><DisconnectedPart><Parts><Part partType="parachute-1" id="174641" x="-2.000000" y="11.250000" angle="3.141593" angleV="0.000000" editorAngle="2" activated="0" exploded="0" flippedX="0" flippedY="0" chuteX="-2.000000" chuteY="11.250000" chuteAngle="0.000000" chuteHeight="0.000000" inflation="0.100000" inflate="0" deployed="0" rope="0"/></Parts><Connections/></DisconnectedPart><DisconnectedPart><Parts><Part partType="lander-1" id="174781" x="1.250000" y="10.250000" angle="1.570796" angleV="0.000000" editorAngle="1" activated="0" exploded="0" flippedX="0" flippedY="0" lower="0" raise="0" length="2.260000" legAngle="0.000000"/></Parts><Connections/></DisconnectedPart><DisconnectedPart><Parts><Part partType="lander-1" id="174779" x="0.750000" y="8.750000" angle="4.712389" angleV="0.000000" editorAngle="3" activated="0" exploded="0" flippedX="0" flippedY="0" lower="0" raise="0" length="2.260000" legAngle="0.000000"/></Parts><Connections/></DisconnectedPart><DisconnectedPart><Parts><Part partType="lander-1" id="174767" x="-2.250000" y="5.750000" angle="3.141593" angleV="0.000000" editorAngle="2" activated="0" exploded="0" flippedX="0" flippedY="0" lower="0" raise="0" length="2.260000" legAngle="0.000000"/></Parts><Connections/></DisconnectedPart><DisconnectedPart><Parts><Part partType="wheel-2" id="174784" x="-1.500000" y="-7.000000" angle="0.000000" angleV="0.000000" editorAngle="0" activated="0" exploded="0" flippedX="0" flippedY="0"/></Parts><Connections/></DisconnectedPart><DisconnectedPart><Parts><Part partType="lander-1" id="174771" x="-27.250000" y="2.750000" angle="0.000000" angleV="0.000000" editorAngle="0" activated="0" exploded="0" flippedX="0" flippedY="0" lower="0" raise="0" length="2.260000" legAngle="0.000000"/></Parts><Connections/></DisconnectedPart><DisconnectedPart><Parts><Part partType="lander-1" id="174772" x="-25.750000" y="4.250000" angle="3.141593" angleV="0.000000" editorAngle="2" activated="0" exploded="0" flippedX="0" flippedY="0" lower="0" raise="0" length="2.260000" legAngle="0.000000"/></Parts><Connections/></DisconnectedPart><DisconnectedPart><Parts><Part partType="strut-1" id="174790" x="-3.500000" y="-5.500000" angle="4.712389" angleV="0.000000" editorAngle="3" activated="0" exploded="0" flippedX="0" flippedY="0"/></Parts><Connections/></DisconnectedPart><DisconnectedPart><Parts><Part partType="parachute-1" id="174666" x="-13.250000" y="-2.000000" angle="4.712389" angleV="0.000000" editorAngle="3" activated="0" exploded="0" flippedX="0" flippedY="0" chuteX="-13.250000" chuteY="-2.000000" chuteAngle="0.000000" chuteHeight="0.000000" inflation="0.100000" inflate="0" deployed="0" rope="0"/></Parts><Connections/></DisconnectedPart><DisconnectedPart><Parts><Part partType="parachute-1" id="174664" x="-12.750000" y="-4.500000" angle="1.570796" angleV="0.000000" editorAngle="1" activated="0" exploded="0" flippedX="0" flippedY="0" chuteX="-12.750000" chuteY="-4.500000" chuteAngle="0.000000" chuteHeight="0.000000" inflation="0.100000" inflate="0" deployed="0" rope="0"/></Parts><Connections/></DisconnectedPart><DisconnectedPart><Parts><Part partType="parachute-1" id="174660" x="-9.250000" y="2.000000" angle="4.712389" angleV="0.000000" editorAngle="3" activated="0" exploded="0" flippedX="0" flippedY="0" chuteX="-9.250000" chuteY="2.000000" chuteAngle="0.000000" chuteHeight="0.000000" inflation="0.100000" inflate="0" deployed="0" rope="0"/></Parts><Connections/></DisconnectedPart><DisconnectedPart><Parts><Part partType="fueltank-5" id="174645" x="15.750000" y="18.750000" angle="0.000000" angleV="0.000000" editorAngle="0"><Tank fuel="275.000000"/></Part></Parts><Connections/></DisconnectedPart><DisconnectedPart><Parts><Part partType="wheel-2" id="175460" x="12.000000" y="19.500000" angle="0.000000" angleV="0.000000" editorAngle="0" activated="0" exploded="0" flippedX="0" flippedY="0"/></Parts><Connections/></DisconnectedPart><DisconnectedPart><Parts><Part partType="dock-1" id="175461" x="10.250000" y="22.500000" angle="4.712389" angleV="0.000000" editorAngle="3" activated="0" exploded="0" flippedX="0" flippedY="0"/></Parts><Connections/></DisconnectedPart></DisconnectedParts><Parts><Part partType="pod-1" id="1" x="22.750000" y="10.000000" angle="4.712389" angleV="0.000000" editorAngle="3"><Pod throttle="0.000000" name="Supershortly"><Staging currentStage="0"><Step><Activate Id="174491" moved="1"/><Activate Id="171722" moved="1"/><Activate Id="171721" moved="1"/><Activate Id="174270" moved="1"/><Activate Id="174702" moved="1"/><Activate Id="174749" moved="1"/><Activate Id="174756" moved="1"/><Activate Id="174757" moved="1"/><Activate Id="174799" moved="1"/></Step><Step><Activate Id="172597" moved="1"/><Activate Id="172594" moved="1"/></Step><Step><Activate Id="174642" moved="1"/><Activate Id="174628" moved="1"/><Activate Id="174639" moved="1"/><Activate Id="174633" moved="1"/><Activate Id="174782" moved="1"/></Step><Step><Activate Id="174446" moved="1"/><Activate Id="174442" moved="1"/></Step><Step><Activate Id="174420" moved="1"/><Activate Id="171733" moved="1"/><Activate Id="174422" moved="1"/><Activate Id="174423" moved="1"/><Activate Id="174424" moved="1"/><Activate Id="174425" moved="1"/><Activate Id="174426" moved="1"/><Activate Id="174427" moved="1"/><Activate Id="174428" moved="1"/><Activate Id="174429" moved="1"/><Activate Id="174430" moved="1"/><Activate Id="174431" moved="1"/><Activate Id="174432" moved="1"/><Activate Id="174433" moved="1"/><Activate Id="174434" moved="1"/><Activate Id="174435" moved="1"/><Activate Id="174436" moved="1"/><Activate Id="174437" moved="1"/><Activate Id="174480" moved="1"/><Activate Id="174789" moved="1"/><Activate Id="174414" moved="1"/></Step><Step><Activate Id="172598" moved="1"/><Activate Id="174447" moved="1"/><Activate Id="174636" moved="1"/><Activate Id="174638" moved="1"/><Activate Id="174780" moved="1"/><Activate Id="174785" moved="1"/><Activate Id="174764" moved="1"/><Activate Id="172596" moved="1"/><Activate Id="174445" moved="1"/><Activate Id="174661" moved="1"/><Activate Id="174777" moved="1"/><Activate Id="174787" moved="1"/><Activate Id="174793" moved="1"/><Activate Id="174792" moved="1"/><Activate Id="174797" moved="1"/><Activate Id="174795" moved="1"/><Activate Id="174796" moved="1"/><Activate Id="174441" moved="1"/><Activate Id="175463" moved="1"/></Step></Staging></Pod></Part><Part partType="strut-1" id="171640" x="24.000000" y="9.500000" angle="4.712389" angleV="0.000000" editorAngle="3" activated="0" exploded="0" flippedX="0" flippedY="0"/><Part partType="strut-1" id="171646" x="19.500000" y="6.000000" angle="0.000000" angleV="0.000000" editorAngle="0" activated="0" exploded="0" flippedX="0" flippedY="0"/><Part partType="strut-1" id="171647" x="11.500000" y="6.000000" angle="0.000000" angleV="0.000000" editorAngle="0" activated="0" exploded="0" flippedX="0" flippedY="0"/><Part partType="wheel-2" id="171722" x="13.250000" y="5.250000" angle="0.000000" angleV="0.000000" editorAngle="0" activated="0" exploded="0" flippedX="0" flippedY="0"/><Part partType="strut-1" id="174753" x="3.500000" y="6.000000" angle="0.000000" angleV="0.000000" editorAngle="0" activated="0" exploded="0" flippedX="0" flippedY="0"/><Part partType="strut-1" id="174657" x="-1.000000" y="7.000000" angle="0.000000" angleV="0.000000" editorAngle="0" activated="0" exploded="0" flippedX="0" flippedY="0"/><Part partType="strut-1" id="174269" x="-8.000000" y="6.000000" angle="0.000000" angleV="0.000000" editorAngle="0" activated="0" exploded="0" flippedX="0" flippedY="0"/><Part partType="strut-1" id="174760" x="-12.750000" y="9.750000" angle="4.712389" angleV="0.000000" editorAngle="3" activated="0" exploded="0" flippedX="0" flippedY="0"/><Part partType="detacher-1" id="171733" x="-13.750000" y="13.500000" angle="4.712389" angleV="0.000000" editorAngle="3" activated="0" exploded="0" flippedX="0" flippedY="0"/><Part partType="fueltank-0" id="174419" x="-14.500000" y="13.500000" angle="4.712389" angleV="0.000000" editorAngle="3"><Tank fuel="750.000000"/></Part><Part partType="parachute-1" id="174414" x="-15.250000" y="13.500000" angle="1.570796" angleV="0.000000" editorAngle="1" activated="0" exploded="0" flippedX="0" flippedY="0" chuteX="-15.250000" chuteY="13.500000" chuteAngle="0.000000" chuteHeight="0.000000" inflation="0.100000" inflate="0" deployed="0" rope="0"/><Part partType="lander-1" id="174422" x="-14.250000" y="12.250000" angle="0.000000" angleV="0.000000" editorAngle="0" activated="0" exploded="0" flippedX="0" flippedY="0" lower="0" raise="0" length="2.260000" legAngle="0.000000"/><Part partType="lander-1" id="174423" x="-14.750000" y="12.250000" angle="0.000000" angleV="0.000000" editorAngle="0" activated="0" exploded="0" flippedX="0" flippedY="0" lower="0" raise="0" length="2.260000" legAngle="0.000000"/><Part partType="lander-1" id="174424" x="-14.750000" y="14.250000" angle="3.141593" angleV="0.000000" editorAngle="2" activated="0" exploded="0" flippedX="0" flippedY="0" lower="0" raise="0" length="2.260000" legAngle="0.000000"/><Part partType="lander-1" id="174425" x="-14.250000" y="14.250000" angle="3.141593" angleV="0.000000" editorAngle="2" activated="0" exploded="0" flippedX="0" flippedY="0" lower="0" raise="0" length="2.260000" legAngle="0.000000"/><Part partType="lander-1" id="174426" x="-14.250000" y="12.250000" angle="0.000000" angleV="0.000000" editorAngle="0" activated="0" exploded="0" flippedX="0" flippedY="0" lower="0" raise="0" length="2.260000" legAngle="0.000000"/><Part partType="lander-1" id="174427" x="-14.750000" y="12.250000" angle="0.000000" angleV="0.000000" editorAngle="0" activated="0" exploded="0" flippedX="0" flippedY="0" lower="0" raise="0" length="2.260000" legAngle="0.000000"/><Part partType="lander-1" id="174428" x="-14.750000" y="14.250000" angle="3.141593" angleV="0.000000" editorAngle="2" activated="0" exploded="0" flippedX="0" flippedY="0" lower="0" raise="0" length="2.260000" legAngle="0.000000"/><Part partType="lander-1" id="174429" x="-14.250000" y="14.250000" angle="3.141593" angleV="0.000000" editorAngle="2" activated="0" exploded="0" flippedX="0" flippedY="0" lower="0" raise="0" length="2.260000" legAngle="0.000000"/><Part partType="lander-1" id="174430" x="-14.250000" y="12.250000" angle="0.000000" angleV="0.000000" editorAngle="0" activated="0" exploded="0" flippedX="0" flippedY="0" lower="0" raise="0" length="2.260000" legAngle="0.000000"/><Part partType="lander-1" id="174431" x="-14.250000" y="12.250000" angle="0.000000" angleV="0.000000" editorAngle="0" activated="0" exploded="0" flippedX="0" flippedY="0" lower="0" raise="0" length="2.260000" legAngle="0.000000"/><Part partType="lander-1" id="174432" x="-14.750000" y="14.250000" angle="3.141593" angleV="0.000000" editorAngle="2" activated="0" exploded="0" flippedX="0" flippedY="0" lower="0" raise="0" length="2.260000" legAngle="0.000000"/><Part partType="lander-1" id="174433" x="-14.250000" y="14.250000" angle="3.141593" angleV="0.000000" editorAngle="2" activated="0" exploded="0" flippedX="0" flippedY="0" lower="0" raise="0" length="2.260000" legAngle="0.000000"/><Part partType="lander-1" id="174434" x="-14.750000" y="12.250000" angle="0.000000" angleV="0.000000" editorAngle="0" activated="0" exploded="0" flippedX="0" flippedY="0" lower="0" raise="0" length="2.260000" legAngle="0.000000"/><Part partType="lander-1" id="174435" x="-14.750000" y="14.250000" angle="3.141593" angleV="0.000000" editorAngle="2" activated="0" exploded="0" flippedX="0" flippedY="0" lower="0" raise="0" length="2.260000" legAngle="0.000000"/><Part partType="lander-1" id="174436" x="-14.750000" y="14.750000" angle="3.141593" angleV="0.000000" editorAngle="2" activated="0" exploded="0" flippedX="0" flippedY="0" lower="0" raise="0" length="2.260000" legAngle="0.000000"/><Part partType="lander-1" id="174437" x="-14.250000" y="12.750000" angle="0.000000" angleV="0.000000" editorAngle="0" activated="0" exploded="0" flippedX="0" flippedY="0" lower="0" raise="0" length="2.260000" legAngle="0.000000"/><Part partType="lander-1" id="174480" x="-14.750000" y="14.750000" angle="1.570796" angleV="0.000000" editorAngle="1" activated="0" exploded="0" flippedX="0" flippedY="0" lower="0" raise="0" length="2.260000" legAngle="0.000000"/><Part partType="lander-1" id="174789" x="-14.750000" y="14.750000" angle="0.000000" angleV="0.000000" editorAngle="0" activated="0" exploded="0" flippedX="0" flippedY="0" lower="0" raise="0" length="2.260000" legAngle="0.000000"/><Part partType="engine-3" id="174420" x="-14.250000" y="10.250000" angle="0.000000" angleV="0.000000" editorAngle="0" activated="0" exploded="0" flippedX="0" flippedY="0"><Engine fuel="0.000000"/></Part><Part partType="wheel-2" id="174270" x="-10.500000" y="5.500000" angle="0.000000" angleV="0.000000" editorAngle="0" activated="0" exploded="0" flippedX="0" flippedY="0"/><Part partType="wheel-2" id="174756" x="-6.500000" y="5.500000" angle="0.000000" angleV="0.000000" editorAngle="0" activated="0" exploded="0" flippedX="0" flippedY="0"/><Part partType="strut-1" id="174794" x="-8.500000" y="10.500000" angle="4.712389" angleV="0.000000" editorAngle="3" activated="0" exploded="0" flippedX="0" flippedY="0"/><Part partType="parachute-1" id="174797" x="-7.750000" y="9.500000" angle="4.712389" angleV="0.000000" editorAngle="3" activated="0" exploded="0" flippedX="0" flippedY="0" chuteX="-7.750000" chuteY="9.500000" chuteAngle="0.000000" chuteHeight="0.000000" inflation="0.100000" inflate="0" deployed="0" rope="0"/><Part partType="strut-1" id="174659" x="-5.500000" y="10.500000" angle="4.712389" angleV="0.000000" editorAngle="3" activated="0" exploded="0" flippedX="0" flippedY="0"/><Part partType="parachute-1" id="174796" x="-6.250000" y="9.500000" angle="1.570796" angleV="0.000000" editorAngle="1" activated="0" exploded="0" flippedX="0" flippedY="0" chuteX="-6.250000" chuteY="9.500000" chuteAngle="0.000000" chuteHeight="0.000000" inflation="0.100000" inflate="0" deployed="0" rope="0"/><Part partType="strut-1" id="174754" x="3.500000" y="10.500000" angle="4.712389" angleV="0.000000" editorAngle="3" activated="0" exploded="0" flippedX="0" flippedY="0"/><Part partType="parachute-1" id="174792" x="4.250000" y="11.500000" angle="4.712389" angleV="0.000000" editorAngle="3" activated="0" exploded="0" flippedX="0" flippedY="0" chuteX="4.250000" chuteY="11.500000" chuteAngle="0.000000" chuteHeight="0.000000" inflation="0.100000" inflate="0" deployed="0" rope="0"/><Part partType="wheel-2" id="174757" x="0.000000" y="5.500000" angle="0.000000" angleV="0.000000" editorAngle="0" activated="0" exploded="0" flippedX="0" flippedY="0"/><Part partType="wheel-2" id="174799" x="6.750000" y="5.750000" angle="0.000000" angleV="0.000000" editorAngle="0" activated="0" exploded="0" flippedX="0" flippedY="0"/><Part partType="wheel-2" id="171721" x="18.000000" y="5.500000" angle="0.000000" angleV="0.000000" editorAngle="0" activated="0" exploded="0" flippedX="0" flippedY="0"/><Part partType="wheel-2" id="174749" x="24.500000" y="11.500000" angle="0.000000" angleV="0.000000" editorAngle="0" activated="0" exploded="0" flippedX="0" flippedY="0"/><Part partType="wheel-2" id="174702" x="24.500000" y="6.000000" angle="0.000000" angleV="0.000000" editorAngle="0" activated="0" exploded="0" flippedX="0" flippedY="0"/><Part partType="fueltank-1" id="174416" x="22.500000" y="8.000000" angle="0.000000" angleV="0.000000" editorAngle="0"><Tank fuel="1500.000000"/></Part><Part partType="engine-1" id="174491" x="20.500000" y="8.000000" angle="4.712389" angleV="0.000000" editorAngle="3" activated="0" exploded="0" flippedX="0" flippedY="0"><Engine fuel="0.000000"/></Part><Part partType="strut-1" id="171659" x="19.500000" y="13.000000" angle="0.000000" angleV="0.000000" editorAngle="0" activated="0" exploded="0" flippedX="0" flippedY="0"/><Part partType="strut-1" id="174625" x="19.250000" y="11.750000" angle="0.000000" angleV="0.000000" editorAngle="0" activated="0" exploded="0" flippedX="0" flippedY="0"/><Part partType="strut-1" id="174630" x="12.000000" y="10.500000" angle="0.000000" angleV="0.000000" editorAngle="0" activated="0" exploded="0" flippedX="0" flippedY="0"/><Part partType="strut-1" id="171661" x="7.500000" y="10.500000" angle="4.712389" angleV="0.000000" editorAngle="3" activated="0" exploded="0" flippedX="0" flippedY="0"/><Part partType="strut-1" id="171664" x="4.000000" y="15.000000" angle="0.000000" angleV="0.000000" editorAngle="0" activated="0" exploded="0" flippedX="0" flippedY="0"/><Part partType="strut-1" id="171668" x="11.000000" y="16.000000" angle="0.000000" angleV="0.000000" editorAngle="0" activated="0" exploded="0" flippedX="0" flippedY="0"/><Part partType="detacher-1" id="174633" x="13.500000" y="15.250000" angle="0.000000" angleV="0.000000" editorAngle="0" activated="0" exploded="0" flippedX="0" flippedY="0"/><Part partType="fueltank-0" id="174634" x="13.500000" y="14.500000" angle="0.000000" angleV="0.000000" editorAngle="0"><Tank fuel="750.000000"/></Part><Part partType="engine-3" id="174628" x="10.500000" y="14.500000" angle="4.712389" angleV="0.000000" editorAngle="3" activated="0" exploded="0" flippedX="0" flippedY="0"><Engine fuel="0.000000"/></Part><Part partType="parachute-1" id="174777" x="8.250000" y="14.500000" angle="1.570796" angleV="0.000000" editorAngle="1" activated="0" exploded="0" flippedX="0" flippedY="0" chuteX="8.250000" chuteY="14.500000" chuteAngle="0.000000" chuteHeight="0.000000" inflation="0.100000" inflate="0" deployed="0" rope="0"/><Part partType="detacher-1" id="174638" x="13.500000" y="13.750000" angle="0.000000" angleV="0.000000" editorAngle="0" activated="0" exploded="0" flippedX="0" flippedY="0"/><Part partType="detacher-1" id="174639" x="13.500000" y="13.250000" angle="0.000000" angleV="0.000000" editorAngle="0" activated="0" exploded="0" flippedX="0" flippedY="0"/><Part partType="fueltank-0" id="174640" x="13.500000" y="12.500000" angle="0.000000" angleV="0.000000" editorAngle="0"><Tank fuel="750.000000"/></Part><Part partType="detacher-1" id="174780" x="13.500000" y="11.750000" angle="0.000000" angleV="0.000000" editorAngle="0" activated="0" exploded="0" flippedX="0" flippedY="0"/><Part partType="engine-3" id="174642" x="10.500000" y="12.500000" angle="4.712389" angleV="0.000000" editorAngle="3" activated="0" exploded="0" flippedX="0" flippedY="0"><Engine fuel="0.000000"/></Part><Part partType="parachute-1" id="174787" x="8.250000" y="12.500000" angle="1.570796" angleV="0.000000" editorAngle="1" activated="0" exploded="0" flippedX="0" flippedY="0" chuteX="8.250000" chuteY="12.500000" chuteAngle="0.000000" chuteHeight="0.000000" inflation="0.100000" inflate="0" deployed="0" rope="0"/><Part partType="wheel-2" id="175463" x="14.500000" y="12.500000" angle="0.000000" angleV="0.000000" editorAngle="0" activated="0" exploded="0" flippedX="0" flippedY="0"/><Part partType="engine-0" id="174636" x="15.000000" y="14.500000" angle="1.570796" angleV="0.000000" editorAngle="1" activated="0" exploded="0" flippedX="0" flippedY="0"><Engine fuel="0.000000"/></Part><Part partType="wheel-2" id="174441" x="6.750000" y="16.250000" angle="0.000000" angleV="0.000000" editorAngle="0" activated="0" exploded="0" flippedX="0" flippedY="0"/><Part partType="strut-1" id="174440" x="2.500000" y="16.500000" angle="0.000000" angleV="0.000000" editorAngle="0" activated="0" exploded="0" flippedX="0" flippedY="0"/><Part partType="detacher-1" id="174442" x="4.000000" y="17.250000" angle="0.000000" angleV="0.000000" editorAngle="0" activated="0" exploded="0" flippedX="0" flippedY="0"/><Part partType="fueltank-0" id="174443" x="4.000000" y="18.000000" angle="0.000000" angleV="0.000000" editorAngle="0"><Tank fuel="750.000000"/></Part><Part partType="parachute-1" id="174445" x="4.000000" y="18.750000" angle="0.000000" angleV="0.000000" editorAngle="0" activated="0" exploded="0" flippedX="0" flippedY="0" chuteX="4.000000" chuteY="18.750000" chuteAngle="0.000000" chuteHeight="0.000000" inflation="0.100000" inflate="0" deployed="0" rope="0"/><Part partType="battery-0" id="174450" x="5.250000" y="18.000000" angle="4.712389" angleV="0.000000" editorAngle="3"><Tank fuel="250.000000"/></Part><Part partType="ion-0" id="174447" x="6.000000" y="18.000000" angle="1.570796" angleV="0.000000" editorAngle="1" activated="0" exploded="0" flippedX="0" flippedY="0"><Engine fuel="0.000000"/></Part><Part partType="fueltank-5" id="174461" x="7.000000" y="18.000000" angle="0.000000" angleV="0.000000" editorAngle="0"><Tank fuel="275.000000"/></Part><Part partType="engine-3" id="174446" x="1.000000" y="18.000000" angle="4.712389" angleV="0.000000" editorAngle="3" activated="0" exploded="0" flippedX="0" flippedY="0"><Engine fuel="0.000000"/></Part><Part partType="strut-1" id="171669" x="19.000000" y="16.000000" angle="0.000000" angleV="0.000000" editorAngle="0" activated="0" exploded="0" flippedX="0" flippedY="0"/><Part partType="lander-1" id="174764" x="23.250000" y="15.750000" angle="4.712389" angleV="0.000000" editorAngle="3" activated="0" exploded="0" flippedX="0" flippedY="0" lower="0" raise="0" length="2.260000" legAngle="0.000000"/><Part partType="strut-1" id="174476" x="-0.500000" y="11.500000" angle="1.570796" angleV="0.000000" editorAngle="1" activated="0" exploded="0" flippedX="0" flippedY="0"/><Part partType="strut-1" id="174475" x="-5.000000" y="15.000000" angle="0.000000" angleV="0.000000" editorAngle="0" activated="0" exploded="0" flippedX="0" flippedY="0"/><Part partType="strut-1" id="171690" x="-9.500000" y="11.500000" angle="4.712389" angleV="0.000000" editorAngle="3" activated="0" exploded="0" flippedX="0" flippedY="0"/><Part partType="strut-1" id="174658" x="-7.000000" y="10.500000" angle="4.712389" angleV="0.000000" editorAngle="3" activated="0" exploded="0" flippedX="0" flippedY="0"/><Part partType="parachute-1" id="174661" x="-7.750000" y="7.500000" angle="1.570796" angleV="0.000000" editorAngle="1" activated="0" exploded="0" flippedX="0" flippedY="0" chuteX="-7.750000" chuteY="7.500000" chuteAngle="0.000000" chuteHeight="0.000000" inflation="0.100000" inflate="0" deployed="0" rope="0"/><Part partType="parachute-1" id="174795" x="-6.250000" y="7.500000" angle="4.712389" angleV="0.000000" editorAngle="3" activated="0" exploded="0" flippedX="0" flippedY="0" chuteX="-6.250000" chuteY="7.500000" chuteAngle="0.000000" chuteHeight="0.000000" inflation="0.100000" inflate="0" deployed="0" rope="0"/><Part partType="strut-1" id="174791" x="5.000000" y="10.500000" angle="4.712389" angleV="0.000000" editorAngle="3" activated="0" exploded="0" flippedX="0" flippedY="0"/><Part partType="parachute-1" id="174793" x="4.250000" y="9.500000" angle="1.570796" angleV="0.000000" editorAngle="1" activated="0" exploded="0" flippedX="0" flippedY="0" chuteX="4.250000" chuteY="9.500000" chuteAngle="0.000000" chuteHeight="0.000000" inflation="0.100000" inflate="0" deployed="0" rope="0"/><Part partType="detacher-1" id="174785" x="13.000000" y="11.250000" angle="0.000000" angleV="0.000000" editorAngle="0" activated="0" exploded="0" flippedX="0" flippedY="0"/><Part partType="lander-1" id="174782" x="13.000000" y="11.500000" angle="4.712389" angleV="0.000000" editorAngle="3" activated="0" exploded="0" flippedX="0" flippedY="0" lower="0" raise="0" length="2.260000" legAngle="0.000000"/><Part partType="detacher-1" id="172594" x="21.500000" y="13.750000" angle="0.000000" angleV="0.000000" editorAngle="0" activated="0" exploded="0" flippedX="0" flippedY="0"/><Part partType="fueltank-0" id="172595" x="21.500000" y="14.500000" angle="0.000000" angleV="0.000000" editorAngle="0"><Tank fuel="750.000000"/></Part><Part partType="engine-0" id="172598" x="23.000000" y="14.500000" angle="1.570796" angleV="0.000000" editorAngle="1" activated="0" exploded="0" flippedX="0" flippedY="0"><Engine fuel="0.000000"/></Part><Part partType="parachute-1" id="172596" x="21.500000" y="15.250000" angle="0.000000" angleV="0.000000" editorAngle="0" activated="0" exploded="0" flippedX="0" flippedY="0" chuteX="21.500000" chuteY="15.250000" chuteAngle="0.000000" chuteHeight="0.000000" inflation="0.100000" inflate="0" deployed="0" rope="0"/><Part partType="engine-3" id="172597" x="18.500000" y="14.500000" angle="4.712389" angleV="0.000000" editorAngle="3" activated="0" exploded="0" flippedX="0" flippedY="0"><Engine fuel="0.000000"/></Part><Part partType="nosecone-1" id="174766" x="16.000000" y="14.500000" angle="1.570796" angleV="0.000000" editorAngle="1" activated="0" exploded="0" flippedX="0" flippedY="0"/></Parts><Connections><Connection parentAttachPoint="1" childAttachPoint="2" parentPart="1" childPart="171640"/><Connection parentAttachPoint="2" childAttachPoint="4" parentPart="171640" childPart="171646"/><Connection parentAttachPoint="3" childAttachPoint="4" parentPart="171646" childPart="171647"/><Connection parentAttachPoint="2" childAttachPoint="1" parentPart="171647" childPart="171722"/><Connection parentAttachPoint="3" childAttachPoint="4" parentPart="171647" childPart="174753"/><Connection parentAttachPoint="1" childAttachPoint="2" parentPart="174753" childPart="174657"/><Connection parentAttachPoint="2" childAttachPoint="1" parentPart="174657" childPart="174269"/><Connection parentAttachPoint="3" childAttachPoint="1" parentPart="174269" childPart="174760"/><Connection parentAttachPoint="2" childAttachPoint="1" parentPart="174760" childPart="171733"/><Connection parentAttachPoint="2" childAttachPoint="1" parentPart="171733" childPart="174419"/><Connection parentAttachPoint="2" childAttachPoint="1" parentPart="174419" childPart="174414"/><Connection parentAttachPoint="4" childAttachPoint="1" parentPart="174419" childPart="174422"/><Connection parentAttachPoint="4" childAttachPoint="2" parentPart="174419" childPart="174423"/><Connection parentAttachPoint="3" childAttachPoint="1" parentPart="174419" childPart="174424"/><Connection parentAttachPoint="3" childAttachPoint="2" parentPart="174419" childPart="174425"/><Connection parentAttachPoint="4" childAttachPoint="1" parentPart="174419" childPart="174426"/><Connection parentAttachPoint="4" childAttachPoint="2" parentPart="174419" childPart="174427"/><Connection parentAttachPoint="3" childAttachPoint="1" parentPart="174419" childPart="174428"/><Connection parentAttachPoint="3" childAttachPoint="2" parentPart="174419" childPart="174429"/><Connection parentAttachPoint="4" childAttachPoint="1" parentPart="174419" childPart="174430"/><Connection parentAttachPoint="4" childAttachPoint="1" parentPart="174419" childPart="174431"/><Connection parentAttachPoint="3" childAttachPoint="1" parentPart="174419" childPart="174432"/><Connection parentAttachPoint="3" childAttachPoint="2" parentPart="174419" childPart="174433"/><Connection parentAttachPoint="4" childAttachPoint="2" parentPart="174419" childPart="174434"/><Connection parentAttachPoint="3" childAttachPoint="1" parentPart="174419" childPart="174435"/><Connection parentAttachPoint="3" childAttachPoint="1" parentPart="174419" childPart="174436"/><Connection parentAttachPoint="4" childAttachPoint="1" parentPart="174419" childPart="174437"/><Connection parentAttachPoint="3" childAttachPoint="1" parentPart="174419" childPart="174480"/><Connection parentAttachPoint="3" childAttachPoint="2" parentPart="174419" childPart="174789"/><Connection parentAttachPoint="4" childAttachPoint="1" parentPart="174419" childPart="174420"/><Connection parentAttachPoint="2" childAttachPoint="1" parentPart="174269" childPart="174270"/><Connection parentAttachPoint="2" childAttachPoint="1" parentPart="174269" childPart="174756"/><Connection parentAttachPoint="1" childAttachPoint="4" parentPart="174269" childPart="174794"/><Connection parentAttachPoint="1" childAttachPoint="1" parentPart="174794" childPart="174797"/><Connection parentAttachPoint="3" childAttachPoint="1" parentPart="174657" childPart="174659"/><Connection parentAttachPoint="2" childAttachPoint="1" parentPart="174659" childPart="174796"/><Connection parentAttachPoint="1" childAttachPoint="4" parentPart="174753" childPart="174754"/><Connection parentAttachPoint="1" childAttachPoint="1" parentPart="174754" childPart="174792"/><Connection parentAttachPoint="2" childAttachPoint="1" parentPart="174753" childPart="174757"/><Connection parentAttachPoint="2" childAttachPoint="1" parentPart="174753" childPart="174799"/><Connection parentAttachPoint="2" childAttachPoint="1" parentPart="171646" childPart="171721"/><Connection parentAttachPoint="1" childAttachPoint="1" parentPart="171640" childPart="174749"/><Connection parentAttachPoint="1" childAttachPoint="1" parentPart="171640" childPart="174702"/><Connection parentAttachPoint="2" childAttachPoint="4" parentPart="171640" childPart="174416"/><Connection parentAttachPoint="3" childAttachPoint="1" parentPart="174416" childPart="174491"/><Connection parentAttachPoint="2" childAttachPoint="4" parentPart="171640" childPart="171659"/><Connection parentAttachPoint="2" childAttachPoint="1" parentPart="171659" childPart="174625"/><Connection parentAttachPoint="2" childAttachPoint="1" parentPart="174625" childPart="174630"/><Connection parentAttachPoint="3" childAttachPoint="1" parentPart="174630" childPart="171661"/><Connection parentAttachPoint="3" childAttachPoint="2" parentPart="171661" childPart="171664"/><Connection parentAttachPoint="1" childAttachPoint="2" parentPart="171664" childPart="171668"/><Connection parentAttachPoint="2" childAttachPoint="1" parentPart="171668" childPart="174633"/><Connection parentAttachPoint="2" childAttachPoint="1" parentPart="174633" childPart="174634"/><Connection parentAttachPoint="3" childAttachPoint="1" parentPart="174634" childPart="174628"/><Connection parentAttachPoint="2" childAttachPoint="1" parentPart="174628" childPart="174777"/><Connection parentAttachPoint="2" childAttachPoint="1" parentPart="174634" childPart="174638"/><Connection parentAttachPoint="2" childAttachPoint="1" parentPart="174638" childPart="174639"/><Connection parentAttachPoint="2" childAttachPoint="1" parentPart="174639" childPart="174640"/><Connection parentAttachPoint="2" childAttachPoint="1" parentPart="174640" childPart="174780"/><Connection parentAttachPoint="3" childAttachPoint="1" parentPart="174640" childPart="174642"/><Connection parentAttachPoint="2" childAttachPoint="1" parentPart="174642" childPart="174787"/><Connection parentAttachPoint="4" childAttachPoint="1" parentPart="174640" childPart="175463"/><Connection parentAttachPoint="4" childAttachPoint="1" parentPart="174634" childPart="174636"/><Connection parentAttachPoint="3" childAttachPoint="1" parentPart="171668" childPart="174441"/><Connection parentAttachPoint="1" childAttachPoint="4" parentPart="174441" childPart="174440"/><Connection parentAttachPoint="1" childAttachPoint="2" parentPart="174440" childPart="174442"/><Connection parentAttachPoint="1" childAttachPoint="2" parentPart="174442" childPart="174443"/><Connection parentAttachPoint="1" childAttachPoint="1" parentPart="174443" childPart="174445"/><Connection parentAttachPoint="4" childAttachPoint="2" parentPart="174443" childPart="174450"/><Connection parentAttachPoint="1" childAttachPoint="1" parentPart="174450" childPart="174447"/><Connection parentAttachPoint="2" childAttachPoint="2" parentPart="174447" childPart="174461"/><Connection parentAttachPoint="3" childAttachPoint="1" parentPart="174443" childPart="174446"/><Connection parentAttachPoint="4" childAttachPoint="3" parentPart="171668" childPart="171669"/><Connection parentAttachPoint="4" childAttachPoint="1" parentPart="171669" childPart="174764"/><Connection parentAttachPoint="3" childAttachPoint="2" parentPart="171664" childPart="174476"/><Connection parentAttachPoint="1" childAttachPoint="4" parentPart="174476" childPart="174475"/><Connection parentAttachPoint="3" childAttachPoint="1" parentPart="174475" childPart="171690"/><Connection parentAttachPoint="2" childAttachPoint="3" parentPart="174475" childPart="174658"/><Connection parentAttachPoint="2" childAttachPoint="1" parentPart="174658" childPart="174661"/><Connection parentAttachPoint="1" childAttachPoint="1" parentPart="174658" childPart="174795"/><Connection parentAttachPoint="2" childAttachPoint="3" parentPart="171664" childPart="174791"/><Connection parentAttachPoint="2" childAttachPoint="1" parentPart="174791" childPart="174793"/><Connection parentAttachPoint="1" childAttachPoint="2" parentPart="174630" childPart="174785"/><Connection parentAttachPoint="1" childAttachPoint="2" parentPart="174785" childPart="174782"/><Connection parentAttachPoint="1" childAttachPoint="2" parentPart="171659" childPart="172594"/><Connection parentAttachPoint="1" childAttachPoint="2" parentPart="172594" childPart="172595"/><Connection parentAttachPoint="4" childAttachPoint="1" parentPart="172595" childPart="172598"/><Connection parentAttachPoint="1" childAttachPoint="1" parentPart="172595" childPart="172596"/><Connection parentAttachPoint="3" childAttachPoint="1" parentPart="172595" childPart="172597"/><Connection parentAttachPoint="2" childAttachPoint="1" parentPart="172597" childPart="174766"/></Connections></Ship>