<Runtime time="0.0" firstStageActivated="1" solarSystem="SmolarSystem.xml">
    <Nodes>
        <ShipNode planet="Smearth" x="25086.400629" y="739149.589172" vx="287.729248" vy="608.873779">
            <Ship currentStage="1" throttle="0.000000" liftedOff="1">
                <Parts>
                    <Part partType="pod-1" id="1" x="25086.400629" y="739149.589172" angle="-0.630828"
                          angleV="-0.001682" activated="0" exploded="0"/>
                    <Part partType="fueltank-2" id="28" x="25084.778650" y="739147.368408" angle="-0.630828"
                          angleV="-0.001682">
                        <Tank fuel="3000"/>
                    </Part>
                    <Part partType="engine-2" id="29" x="25082.714319" y="739144.541992" angle="-0.630820"
                          angleV="-0.001677" activated="1" exploded="0"/>
                </Parts>
                <Connections>
                    <Connection parentPart="1" parentAttachPoint="2" childPart="28" childAttachPoint="1"/>
                    <Connection parentPart="28" parentAttachPoint="2" childPart="29" childAttachPoint="1"/>
                </Connections>
                <Staging>
                    <Step>
                        <Activate Id="29"/>
                    </Step>
                </Staging>
            </Ship>
        </ShipNode>
        <PlanetNode name="Smercury" trueAnomaly="-2.465148"/>
        <PlanetNode name="Smenus" trueAnomaly="0.822420"/>
        <PlanetNode name="Smearth" trueAnomaly="-3.013170"/>
        <PlanetNode name="Smoon" trueAnomaly="-2.138368"/>
        <PlanetNode name="Smars" trueAnomaly="1.734006"/>
        <PlanetNode name="Smupiter" trueAnomaly="1.324001"/>
        <PlanetNode name="Smaturn" trueAnomaly="2.222000"/>
        <PlanetNode name="Smuranus" trueAnomaly="-2.839185"/>
        <PlanetNode name="Smeptune" trueAnomaly="-1.313185"/>
    </Nodes>
</Runtime>
